Workbook

Sheet Alert

Sheet WCP_42M
C2: Cash Flow and Valuation
C3: Woodfine Capital Projects Inc.
C4: Mathew Woodfine
C5: January 6, 2026
C6: V3
B9: 1 | C9: Number of Common Shares | F9: 10000000
B10: 2 | C10: Price per Share — CAD | F10: 20
B11: 3 | C11: CAD-USD | F11: 1.3372
B12: 4 | C12: CAD-EUR | F12: 1.4657
B13: 5 | C13: Financing Activity — WCP Common Shares | F13: 42000000
B14: 6
B15: 7 | C15: WCP Pro Forma Income Statement
B16: 8 | C16: ** In Canadian Dollars
B17: 9 | C17: Revenue and Assets from the Woodfine LPs
B18: 10
B19: 11 | G19: Y0 | H19: Y0 | I19: Y1 | J19: Y2 | K19: Y3 | L19: Y4 | M19: Y5 | N19: Y6 | O19: Y7 | P19: Y8 | Q19: Y9 | R19: Y10
B20: 12 | C20: Woodfine Professional Centres Limited Partnership (Canada) — C$250 million GFV
B21: 13 | D21: Advisory Fee | G21: =('INPUT_PCLP 1_250M'!E63)*(1/3) -> 833333.33 | H21: =('INPUT_PCLP 1_250M'!F63)*(2/3) -> 1666666.7 | I21: =('INPUT_PCLP 1_250M'!G63)*(3/3) -> 2500000 | J21: =('INPUT_PCLP 1_250M'!H63)*(3/3) -> 2500000 | K21: =('INPUT_PCLP 1_250M'!I63)*(3/3) -> 2500000 | L21: =('INPUT_PCLP 1_250M'!J63)*(3/3) -> 2500000 | M21: =('INPUT_PCLP 1_250M'!K63)*(3/3) -> 2500000 | N21: =('INPUT_PCLP 1_250M'!L63)*(3/3) -> 2500000 | O21: =('INPUT_PCLP 1_250M'!M63)*(3/3) -> 2500000 | P21: =('INPUT_PCLP 1_250M'!N63)*(3/3) -> 2500000 | ... R21: =('INPUT_PCLP 1_250M'!P63)*(3/3) -> 2500000
B22: 14 | D22: Distributions | G22: =('INPUT_PCLP 1_250M'!E120)*(1/10) -> 0 | H22: =('INPUT_PCLP 1_250M'!F120)*(1/10) -> 0 | I22: =('INPUT_PCLP 1_250M'!G120)*(1/10) -> 0 | J22: =('INPUT_PCLP 1_250M'!H120)*(1/10) -> 400461.48 | K22: =('INPUT_PCLP 1_250M'!I120)*(1/10) -> 558217.75 | L22: =('INPUT_PCLP 1_250M'!J120)*(1/10) -> 791131.91 | M22: =('INPUT_PCLP 1_250M'!K120)*(1/10) -> 1180360.4 | N22: =('INPUT_PCLP 1_250M'!L120)*(1/10) -> 6692171.2 | ... R22: =('INPUT_PCLP 1_250M'!P120)*(1/10) -> 6827021.8
B23: 15 | D23: Net Asset Value — Public Non-Listed | G23: =('INPUT_PCLP 1_250M'!E114)*(1/10) -> 27785000 | H23: =('INPUT_PCLP 1_250M'!F114)*(1/10) -> 27847838 | I23: =('INPUT_PCLP 1_250M'!G114)*(1/10) -> 27826893 | J23: =('INPUT_PCLP 1_250M'!H114)*(1/10) -> 37018888 | K23: =('INPUT_PCLP 1_250M'!I114)*(1/10) -> 37080913 | L23: =('INPUT_PCLP 1_250M'!J114)*(1/10) -> 60254816 | M23: =('INPUT_PCLP 1_250M'!K114)*(1/10) -> 60385967 | N23: =('INPUT_PCLP 1_250M'!L114)*(1/10) -> 1.0565254e+08 | ... R23: =('INPUT_PCLP 1_250M'!P114)*(1/10) -> 1.2658516e+08
B24: 16
B25: 17 | C25: Woodfine Professional Centres 2 Limited Partnership (US) — US$500 million GFV
B26: 18 | D26: Advisory Fee | H26: =(G21*2)*$F11 -> 2228666.7 | I26: =(H21*2)*$F11 -> 4457333.3 | J26: =(I21*2)*$F11 -> 6686000 | K26: =(J21*2)*$F11 -> 6686000 | L26: =(K21*2)*$F11 -> 6686000 | M26: =(L21*2)*$F11 -> 6686000 | N26: =(M21*2)*$F11 -> 6686000 | O26: =(N21*2)*$F11 -> 6686000 | ... R26: =(Q21*2)*$F11 -> 6686000
B27: 19 | D27: Distributions | H27: =(G22*2)*$F11 -> 0 | I27: =(H22*2)*$F11 -> 0 | J27: =(I22*2)*$F11 -> 0 | K27: =(J22*2)*$F11 -> 1070994.2 | L27: =(K22*2)*$F11 -> 1492897.5 | M27: =(L22*2)*$F11 -> 2115803.2 | N27: =(M22*2)*$F11 -> 3156755.9 | O27: =(N22*2)*$F11 -> 17897543 | ... R27: =(Q22*2)*$F11 -> 18167350
B28: 20 | D28: Net Asset Value — Public Non-Listed | H28: =(G23*2)*$F11 -> 74308204 | I28: =(H23*2)*$F11 -> 74476258 | J28: =(I23*2)*$F11 -> 74420242 | K28: =(J23*2)*$F11 -> 99003315 | L28: =(K23*2)*$F11 -> 99169193 | M28: =(L23*2)*$F11 -> 1.6114548e+08 | N28: =(M23*2)*$F11 -> 1.6149623e+08 | O28: =(N23*2)*$F11 -> 2.8255716e+08 | ... R28: =(Q23*2)*$F11 -> 3.3651067e+08
B29: 21
B30: 22 | C30: Woodfine Professional Centres 3 Limited Partnership (Spain) — EUR$250 million GFV
B31: 23 | D31: Advisory Fee | H31: =(G21)*$F12 -> 1221416.7 | I31: =(H21)*$F12 -> 2442833.3 | J31: =(I21)*$F12 -> 3664250 | K31: =(J21)*$F12 -> 3664250 | L31: =(K21)*$F12 -> 3664250 | M31: =(L21)*$F12 -> 3664250 | N31: =(M21)*$F12 -> 3664250 | O31: =(N21)*$F12 -> 3664250 | ... R31: =(Q21)*$F12 -> 3664250
B32: 24 | D32: Distributions | H32: =(G22)*$F12 -> 0 | I32: =(H22)*$F12 -> 0 | J32: =(I22)*$F12 -> 0 | K32: =(J22)*$F12 -> 586956.39 | L32: =(K22)*$F12 -> 818179.76 | M32: =(L22)*$F12 -> 1159562 | N32: =(M22)*$F12 -> 1730054.3 | O32: =(N22)*$F12 -> 9808715.3 | ... R32: =(Q22)*$F12 -> 9956582.9
B33: 25 | D33: Net Asset Value — Public Non-Listed | H33: =(G23)*$F12 -> 40724474 | I33: =(H23)*$F12 -> 40816576 | J33: =(I23)*$F12 -> 40785877 | K33: =(J23)*$F12 -> 54258585 | L33: =(K23)*$F12 -> 54349494 | M33: =(L23)*$F12 -> 88315484 | N33: =(M23)*$F12 -> 88507712 | O33: =(N23)*$F12 -> 1.5485493e+08 | ... R33: =(Q23)*$F12 -> 1.8442405e+08
B34: 26
B35: 27 | C35: Woodfine Professional Centres 4 Limited Partnership (Mexico) — US$250 million GFV
B36: 28 | D36: Advisory Fee | I36: =(G21)*$F11 -> 1114333.3 | J36: =(H21)*$F11 -> 2228666.7 | K36: =(I21)*$F11 -> 3343000 | L36: =(J21)*$F11 -> 3343000 | M36: =(K21)*$F11 -> 3343000 | N36: =(L21)*$F11 -> 3343000 | O36: =(M21)*$F11 -> 3343000 | P36: =(N21)*$F11 -> 3343000 | ... R36: =(P21)*$F11 -> 3343000
B37: 29 | D37: Distributions | I37: =(G22)*$F11 -> 0 | J37: =(H22)*$F11 -> 0 | K37: =(I22)*$F11 -> 0 | L37: =(J22)*$F11 -> 535497.09 | M37: =(K22)*$F11 -> 746448.77 | N37: =(L22)*$F11 -> 1057901.6 | O37: =(M22)*$F11 -> 1578377.9 | P37: =(N22)*$F11 -> 8948771.3 | ... R37: =(P22)*$F11 -> 9038482.8
B38: 30 | D38: Net Asset Value — Public Non-Listed | I38: =(G23)*$F11 -> 37154102 | J38: =(H23)*$F11 -> 37238129 | K38: =(I23)*$F11 -> 37210121 | L38: =(J23)*$F11 -> 49501658 | M38: =(K23)*$F11 -> 49584596 | N38: =(L23)*$F11 -> 80572740 | O38: =(M23)*$F11 -> 80748115 | P38: =(N23)*$F11 -> 1.4127858e+08 | ... R38: =(P23)*$F11 -> 1.4328213e+08
B39: 31
B40: 32 | C40: Woodfine Vertical Warehouse Limited Partnership (US) — US$250 million GFV
B41: 33 | D41: Advisory Fee | J41: =(G21)*$F11 -> 1114333.3 | K41: =(H21)*$F11 -> 2228666.7 | L41: =(I21)*$F11 -> 3343000 | M41: =(J21)*$F11 -> 3343000 | N41: =(K21)*$F11 -> 3343000 | O41: =(L21)*$F11 -> 3343000 | P41: =(M21)*$F11 -> 3343000 | Q41: =(N21)*$F11 -> 3343000 | R41: =(O21)*$F11 -> 3343000
B42: 34 | D42: Distributions | J42: =(G22)*$F12 -> 0 | K42: =(H22)*$F12 -> 0 | L42: =(I22)*$F12 -> 0 | M42: =(J22)*$F12 -> 586956.39 | N42: =(K22)*$F12 -> 818179.76 | O42: =(L22)*$F12 -> 1159562 | P42: =(M22)*$F12 -> 1730054.3 | Q42: =(N22)*$F12 -> 9808715.3 | R42: =(O22)*$F12 -> 9857758.9
B43: 35 | D43: Net Asset Value — Public Non-Listed | J43: =(G23)*$F11 -> 37154102 | K43: =(H23)*$F11 -> 37238129 | L43: =(I23)*$F11 -> 37210121 | M43: =(J23)*$F11 -> 49501658 | N43: =(K23)*$F11 -> 49584596 | O43: =(L23)*$F11 -> 80572740 | P43: =(M23)*$F11 -> 80748115 | Q43: =(N23)*$F11 -> 1.4127858e+08 | R43: =(O23)*$F11 -> 1.4227786e+08
B44: 36
B45: 37 | C45: Woodfine Parking Structures Limited Partnership (US) — US$250 million GFV
B46: 38 | D46: Advisory Fee | K46: =(G21)*$F11 -> 1114333.3 | L46: =(H21)*$F11 -> 2228666.7 | M46: =(I21)*$F11 -> 3343000 | N46: =(J21)*$F11 -> 3343000 | O46: =(K21)*$F11 -> 3343000 | P46: =(L21)*$F11 -> 3343000 | Q46: =(M21)*$F11 -> 3343000 | R46: =(N21)*$F11 -> 3343000
B47: 39 | D47: Distributions | K47: =(G22)*$F12 -> 0 | L47: =(H22)*$F12 -> 0 | M47: =(I22)*$F12 -> 0 | N47: =(J22)*$F12 -> 586956.39 | O47: =(K22)*$F12 -> 818179.76 | P47: =(L22)*$F12 -> 1159562 | Q47: =(M22)*$F12 -> 1730054.3 | R47: =(N22)*$F12 -> 9808715.3
B48: 40 | D48: Net Asset Value — Public Non-Listed | K48: =(G23)*$F11 -> 37154102 | L48: =(H23)*$F11 -> 37238129 | M48: =(I23)*$F11 -> 37210121 | N48: =(J23)*$F11 -> 49501658 | O48: =(K23)*$F11 -> 49584596 | P48: =(L23)*$F11 -> 80572740 | Q48: =(M23)*$F11 -> 80748115 | R48: =(N23)*$F11 -> 1.4127858e+08
B49: 41
B50: 42 | C50: Woodfine Professional Centres 5 Limited Partnership (Greece) — EUR$250 million GFV
B51: 43 | C51: Woodfine Professional Centres 6 Limited Partnership LP (Italy) — EUR$250 million GFV
B52: 44
B53: 45 | C53: Offering Costs Reimbursement | G53: =G21 -> 833333.33 | H53: =SUM(H21+H26+H31+H36+H41+H46)-SUM(G53:G53) -> 4283416.7 | I53: =SUM(I21+I26+I31+I36+I41+I46)-SUM(G53:H53) -> 5397750 | J53: =SUM(J21+J26+J31+J36+J41+J46)-SUM(G53:I53) -> 5678750 | K53: =SUM(K21+K26+K31+K36+K41+K46)-SUM(G53:J53) -> 3343000 | L53: =SUM(L21+L26+L31+L36+L41+L46)-SUM(G53:K53) -> 2228666.7 | M53: 0 | N53: 0 | O53: 0 | P53: 0 | Q53: 0 | R53: 0
B54: 46
B55: 47 | C55: Gross Income | G55: =(SUM(G21:G22)+SUM(G26:G27)+SUM(G31:G32))+SUM(G36:G37)+SUM(G41:G42)+SUM(G46:G47)+SUM(G53) -> 1666666.7 | H55: =(SUM(H21:H22)+SUM(H26:H27)+SUM(H31:H32))+SUM(H36:H37)+SUM(H41:H42)+SUM(H46:H47)+SUM(H53) -> 9400166.7 | I55: =(SUM(I21:I22)+SUM(I26:I27)+SUM(I31:I32))+SUM(I36:I37)+SUM(I41:I42)+SUM(I46:I47)+SUM(I53) -> 15912250 | J55: =(SUM(J21:J22)+SUM(J26:J27)+SUM(J31:J32))+SUM(J36:J37)+SUM(J41:J42)+SUM(J46:J47)+SUM(J53) -> 22272461 | K55: =(SUM(K21:K22)+SUM(K26:K27)+SUM(K31:K32))+SUM(K36:K37)+SUM(K41:K42)+SUM(K46:K47)+SUM(K53) -> 25095418 | L55: =(SUM(L21:L22)+SUM(L26:L27)+SUM(L31:L32))+SUM(L36:L37)+SUM(L41:L42)+SUM(L46:L47)+SUM(L53) -> 27631290 | M55: =(SUM(M21:M22)+SUM(M26:M27)+SUM(M31:M32))+SUM(M36:M37)+SUM(M41:M42)+SUM(M46:M47)+SUM(M53) -> 28668381 | N55: =(SUM(N21:N22)+SUM(N26:N27)+SUM(N31:N32))+SUM(N36:N37)+SUM(N41:N42)+SUM(N46:N47)+SUM(N53) -> 36921269 | ... R55: =(SUM(R21:R22)+SUM(R26:R27)+SUM(R31:R32))+SUM(R36:R37)+SUM(R41:R42)+SUM(R46:R47)+SUM(R53) -> 86535162
B56: 48
B57: 49 | C57: Operating Expenses
B58: 50 | C58: Referral Fees Paid on the Sale of Shares | G58: =G72*0.1 -> 2000000 | H58: =H72*0.1 -> 2200000 | I58: 0 | J58: =J72*0.1 -> 0 | K58: =K72*0.1 -> 0 | L58: =L72*0.1 -> 0 | M58: =M72*0.1 -> 0 | N58: =N72*0.1 -> 0 | O58: =O72*0.1 -> 0 | P58: =P72*0.1 -> 0 | Q58: =Q72*0.1 -> 0 | R58: =R72*0.1 -> 0
B59: 51 | C59: WPI Consulting Agreement | F59: =SUM(G59:R59) -> 10500000 | G59: 2000000 | H59: 8500000 | I59: 0 | J59: =J73*0.1 -> 0 | K59: =K73*0.1 -> 0 | L59: =L73*0.1 -> 0 | M59: =M73*0.1 -> 0 | N59: =N73*0.1 -> 0 | O59: =O73*0.1 -> 0 | P59: =P73*0.1 -> 0 | Q59: =Q73*0.1 -> 0 | R59: =R73*0.1 -> 0
B60: 52 | C60: General and Administration — New York City | G60: 750000 | H60: 750000 | I60: =(I21+I26+I31+I36+I41+I46)*20%*70% -> 1472030 | J60: =(J21+J26+J31+J36+J41+J46)*25%*70% -> 2833818.8 | K60: =(K21+K26+K31+K36+K41+K46)*30%*70% -> 4102612.5 | L60: =(L21+L26+L31+L36+L41+L46)*35%*70% -> 5332404.6 | M60: =(M21+M26+M31+M36+M41+M46)*40%*70% -> 6406190 | N60: =(N21+N26+N31+N36+N41+N46)*45%*70% -> 7206963.8 | O60: =(O21+O26+O31+O36+O41+O46)*50%*70% -> 8007737.5 | P60: =(P21+P26+P31+P36+P41+P46)*55%*70% -> 8808511.2 | Q60: =(Q21+Q26+Q31+Q36+Q41+Q46)*60%*70% -> 9609285 | R60: =(R21+R26+R31+R36+R41+R46)*65%*70% -> 10410059
B61: 53 | C61: General and Administration — Berlin | G61: 0 | H61: 250000 | I61: =(I21+I26+I31+I36+I41+I46)*20%*30% -> 630870 | J61: =(J21+J26+J31+J36+J41+J46)*25%*30% -> 1214493.8 | K61: =(K21+K26+K31+K36+K41+K46)*30%*30% -> 1758262.5 | L61: =(L21+L26+L31+L36+L41+L46)*35%*30% -> 2285316.2 | M61: =(M21+M26+M31+M36+M41+M46)*40%*30% -> 2745510 | N61: =(N21+N26+N31+N36+N41+N46)*45%*30% -> 3088698.8 | O61: =(O21+O26+O31+O36+O41+O46)*50%*30% -> 3431887.5 | P61: =(P21+P26+P31+P36+P41+P46)*55%*30% -> 3775076.3 | Q61: =(Q21+Q26+Q31+Q36+Q41+Q46)*60%*30% -> 4118265 | R61: =(R21+R26+R31+R36+R41+R46)*65%*30% -> 4461453.8
B62: 54 | C62: Total Operating Expenses | G62: =SUM(G58:G61) -> 4750000 | H62: =SUM(H58:H61) -> 11700000 | I62: =SUM(I58:I61) -> 2102900 | J62: =SUM(J58:J61) -> 4048312.5 | K62: =SUM(K58:K61) -> 5860875 | L62: =SUM(L58:L61) -> 7617720.8 | M62: =SUM(M58:M61) -> 9151700 | N62: =SUM(N58:N61) -> 10295662 | ... R62: =SUM(R58:R61) -> 14871512
B63: 55
B64: 56 | C64: EBITDA | G64: =G55-G62 -> -3083333.3 | H64: =H55-H62 -> -2299833.3 | I64: =I55-I62 -> 13809350 | J64: =J55-J62 -> 18224149 | K64: =K55-K62 -> 19234543 | L64: =L55-L62 -> 20013569 | M64: =M55-M62 -> 19516681 | N64: =N55-N62 -> 26625607 | ... R64: =R55-R62 -> 71663650
B65: 57 | D65: Per Share | G65: =G64/F9 -> -0.30833333 | H65: =H64/F9 -> -0.22998333 | I65: =I64/$F$9 -> 1.380935 | J65: =J64/$F$9 -> 1.8224149 | K65: =K64/$F$9 -> 1.9234543 | L65: =L64/$F$9 -> 2.0013569 | M65: =M64/$F$9 -> 1.9516681 | N65: =N64/$F$9 -> 2.6625607 | O65: =O64/$F$9 -> 4.9427635 | P65: =P64/$F$9 -> 5.67381 | ... R65: =R64/$F$9 -> 7.166365
B66: 58
B67: 59 | C67: Taxes | D67: Effective Tax Rate | F67: 0.27 | G67: =$F67*G64 -> -832500 | H67: =$F67*H64 -> -620955 | I67: =$F67*I64 -> 3728524.5 | J67: =$F67*J64 -> 4920520.2 | K67: =$F67*K64 -> 5193326.7 | L67: =$F67*L64 -> 5403663.6 | M67: =$F67*M64 -> 5269503.8 | N67: =$F67*N64 -> 7188913.8 | ... R67: =$F67*R64 -> 19349185
B68: 60
B69: 61 | C69: Earnings | G69: =G64-G67 -> -2250833.3 | H69: =H64-H67 -> -1678878.3 | I69: =I64-I67 -> 10080826 | J69: =J64-J67 -> 13303629 | K69: =K64-K67 -> 14041217 | L69: =L64-L67 -> 14609905 | M69: =M64-M67 -> 14247177 | N69: =N64-N67 -> 19436693 | ... R69: =R64-R67 -> 52314464
B70: 62 | D70: Per Share | G70: =G69/$F9 -> -0.22508333 | H70: =H69/$F9 -> -0.16788783 | I70: =I69/$F9 -> 1.0080825 | J70: =J69/$F9 -> 1.3303629 | K70: =K69/$F9 -> 1.4041217 | L70: =L69/$F9 -> 1.4609905 | M70: =M69/$F9 -> 1.4247177 | N70: =N69/$F9 -> 1.9436693 | ... R70: =R69/$F9 -> 5.2314464
B71: 63
B72: 64 | C72: Financing Activity — WCP Common Shares | G72: 20000000 | H72: 22000000
B73: 65
B74: 66 | C74: Book Valuation | G74: Y0 | H74: Y0 | I74: Y1 | J74: Y2 | K74: Y3 | L74: Y4 | M74: Y5 | N74: Y6 | O74: Y7 | P74: Y8 | Q74: Y9 | R74: Y10
B75: 67 | D75: Cumulative Free Cash Flow — Woodfine Credit Inc. | G75: =G72+G69 -> 17749167 | H75: =G75+H69+H72 -> 38070288 | I75: =I72+I69+H75 -> 48151114 | J75: =J72+J69+I75 -> 61454743 | K75: =K72+K69+J75 -> 75495959 | L75: =L72+L69+K75 -> 90105864 | M75: =M72+M69+L75 -> 1.0435304e+08 | N75: =N72+N69+M75 -> 1.2378973e+08 | O75: =O72+O69+N75 -> 1.5987191e+08 | P75: =P72+P69+O75 -> 2.0129072e+08 | ... R75: =R72+R69+Q75 -> 3.0066175e+08
B76: 68 | D76: 10% Beneficial Ownership in the Woodfine LPs | G76: =(G23+G28+G33) -> 27785000 | H76: =H23+H28+H33+H38+H43+H48 -> 1.4288052e+08 | I76: =I23+I28+I33+I38+I43+I48 -> 1.8027383e+08 | J76: =J23+J28+J33+J38+J43+J48 -> 2.2661724e+08 | K76: =K23+K28+K33+K38+K43+K48 -> 3.0194516e+08 | L76: =L23+L28+L33+L38+L43+L48 -> 3.3772341e+08 | M76: =M23+M28+M33+M38+M43+M48 -> 4.4614331e+08 | N76: =N23+N28+N33+N38+N43+N48 -> 5.3531548e+08 | O76: =O23+O28+O33+O38+O43+O48 -> 7.5471737e+08 | ... R76: =R23+R28+R33+R38+R43+R48 -> 1.0743585e+09
B77: 69 | D77: Book Value | G77: =SUM(G75:G76) -> 45534167 | H77: =SUM(H75:H76) -> 1.809508e+08 | I77: =SUM(I75:I76) -> 2.2842494e+08 | J77: =SUM(J75:J76) -> 2.8807198e+08 | K77: =SUM(K75:K76) -> 3.7744112e+08 | L77: =SUM(L75:L76) -> 4.2782927e+08 | M77: =SUM(M75:M76) -> 5.5049635e+08 | N77: =SUM(N75:N76) -> 6.5910521e+08 | ... R77: =SUM(R75:R76) -> 1.3750202e+09
B78: 70 | D78: Book Value per Share | G78: =SUM(G75:G76)/$F9 -> 4.5534167 | H78: =SUM(H75:H76)/$F9 -> 18.09508 | I78: =SUM(I75:I76)/$F9 -> 22.842494 | J78: =SUM(J75:J76)/$F9 -> 28.807198 | K78: =SUM(K75:K76)/$F9 -> 37.744112 | L78: =SUM(L75:L76)/$F9 -> 42.782927 | M78: =SUM(M75:M76)/$F9 -> 55.049635 | N78: =SUM(N75:N76)/$F9 -> 65.910521 | ... R78: =SUM(R75:R76)/$F9 -> 137.50202
B79: 71
B80: 72 | C80: Market Valuation
B81: 73 | D81: Earnings Valuation | F81: 10.72 | G81: =G69*$F81 -> -24128933 | H81: =H69*$F81 -> -17997576 | I81: =I69*$F81 -> 1.0806645e+08 | J81: =J69*$F81 -> 1.426149e+08 | K81: =K69*$F81 -> 1.5052184e+08 | L81: =L69*$F81 -> 1.5661818e+08 | M81: =M69*$F81 -> 1.5272974e+08 | N81: =N69*$F81 -> 2.0836135e+08 | ... R81: =R69*$F81 -> 5.6081106e+08
B82: 74 | D82: Cumulative Free Cash Flow — Woodfine Credit Inc. | G82: =G75 -> 17749167 | H82: =H75 -> 38070288 | I82: =I75 -> 48151114 | J82: =J75 -> 61454743 | K82: =K75 -> 75495959 | L82: =L75 -> 90105864 | M82: =M75 -> 1.0435304e+08 | N82: =N75 -> 1.2378973e+08 | ... R82: =R75 -> 3.0066175e+08
B83: 75 | D83: Market Valuation | G83: =SUM(G81:G82) -> -6379766.7 | H83: =SUM(H81:H82) -> 20072713 | I83: =SUM(I81:I82) -> 1.5621756e+08 | J83: =SUM(J81:J82) -> 2.0406964e+08 | K83: =SUM(K81:K82) -> 2.260178e+08 | L83: =SUM(L81:L82) -> 2.4672405e+08 | M83: =SUM(M81:M82) -> 2.5708278e+08 | N83: =SUM(N81:N82) -> 3.3215108e+08 | ... R83: =SUM(R81:R82) -> 8.6147281e+08
B84: 76 | D84: P/E Ratio | G84: =G83/G69 -> 2.8344021 | H84: =H83/H69 -> -11.956026 | I84: =I83/I69 -> 15.496505 | J84: =J83/J69 -> 15.339397 | K84: =K83/K69 -> 16.096739 | L84: =L83/L69 -> 16.88745 | M84: =M83/M69 -> 18.044471 | N84: =N83/N69 -> 17.088868 | ... R84: =R83/R69 -> 16.467201
B85: 77 | D85: Market Valuation per Share | G85: =(SUM(G81:G82))/$F9 -> -0.63797667 | H85: =(SUM(H81:H82))/$F9 -> 2.0072713 | I85: =(SUM(I81:I82))/$F9 -> 15.621756 | J85: =(SUM(J81:J82))/$F9 -> 20.406964 | K85: =(SUM(K81:K82))/$F9 -> 22.60178 | L85: =(SUM(L81:L82))/$F9 -> 24.672405 | M85: =(SUM(M81:M82))/$F9 -> 25.708278 | N85: =(SUM(N81:N82))/$F9 -> 33.215108 | ... R85: =(SUM(R81:R82))/$F9 -> 86.147281
B86: 78
B87: 79 | C87: Fair Valuation
B88: 80 | D88: Equity Growth — YoY | G88: =(G75-0)/G75 -> 1 | H88: =(H75-G75)/G75 -> 1.1449057 | I88: =(I75-H75)/H75 -> 0.26479509 | J88: =(J75-I75)/I75 -> 0.27628912 | K88: =(K75-J75)/J75 -> 0.2284806 | L88: =(L75-K75)/K75 -> 0.19351904 | M88: =(M75-L75)/L75 -> 0.15811598 | N88: =(N75-M75)/M75 -> 0.186259 | O88: =(O75-N75)/N75 -> 0.29147953 | ... R88: =(R75-Q75)/Q75 -> 0.21065043
B89: 81 | D89: Asset Growth — YoY | G89: =(G76-0)/G76 -> 1 | H89: =(H76-G76)/G76 -> 4.1423616 | I89: =(I76-H76)/H76 -> 0.26171036 | J89: =(J76-I76)/I76 -> 0.25707231 | K89: =(K76-J76)/J76 -> 0.33240157 | L89: =(L76-K76)/K76 -> 0.11849253 | M89: =(M76-L76)/L76 -> 0.32103163 | N89: =(N76-M76)/M76 -> 0.19987338 | O89: =(O76-N76)/N76 -> 0.40985532 | ... R89: =(R76-Q76)/Q76 -> 0.15058908
B90: 82 | D90: Earnings Growth — YoY | G90: =(0-G70)/ABS(G70) -> 1 | H90: =(H70-G70)/ABS(G70) -> 0.25410811 | I90: =(I70-H70)/ABS(H70) -> 7.0045003 | J90: =(J70-I70)/ABS(I70) -> 0.31969636 | K90: =(K70-J70)/ABS(J70) -> 0.055442607 | L90: =(L70-K70)/ABS(K70) -> 0.040501377 | M90: =(M70-L70)/ABS(L70) -> -0.024827556 | N90: =(N70-M70)/ABS(M70) -> 0.36424871 | O90: =(O70-N70)/ABS(N70) -> 0.8563947 | ... R90: =(R70-Q70)/ABS(Q70) -> 0.11173561
B91: 83 | D91: Earnings Growth — Forward Moving Average | E91: PEG Ratio | F91: 1 | G91: =AVERAGE(H90:R90) -> 0.84234713 | H91: =AVERAGE(I90:R90) -> 0.90117104 | I91: =AVERAGE(J90:R90) -> 0.22302334 | J91: =AVERAGE(K90:R90) -> 0.21093921 | K91: =AVERAGE(L90:R90) -> 0.23315301 | L91: =AVERAGE(M90:R90) -> 0.26526161 | M91: =AVERAGE(N90:R90) -> 0.32327945 | N91: =AVERAGE(O90:R90) -> 0.31303713 | O91: =AVERAGE(P90:R90) -> 0.13191795 | P91: =AVERAGE(Q90:R90) -> 0.12392573 | Q91: =AVERAGE(R90) -> 0.11173561 | R91: =AVERAGE(R90) -> 0.11173561
B92: 84 | D92: Fair Valuation per Share | G92: =((G91*100)*$F91*G70)+(G82/$F9) -> -17.184913 | H92: =((H91*100)*$F91*H70)+(H82/$F9) -> -11.322536 | I92: =((I91*100)*$F91*I70)+(I82/$F9) -> 27.297705 | J92: =((J91*100)*$F91*J70)+(J82/$F9) -> 34.208044 | K92: =((K91*100)*$F91*K70)+(K82/$F9) -> 40.287115 | L92: =((L91*100)*$F91*L70)+(L82/$F9) -> 47.765057 | M92: =((M91*100)*$F91*M70)+(M82/$F9) -> 56.493499 | N92: =((N91*100)*$F91*N70)+(N82/$F9) -> 73.22304 | ... R92: =((R91*100)*$F91*R70)+(R82/$F9) -> 88.52006
B93: 85
B94: 86 | C94: Dividend Valuation
B95: 87 | D95: Free Cash Flow — Available for Distribution | E95: Dividend Yield | F95: 0.045 | G95: =G69 -> -2250833.3 | H95: =H69 -> -1678878.3 | I95: =I69 -> 10080826 | J95: =J69 -> 13303629 | K95: =K69 -> 14041217 | L95: =L69 -> 14609905 | M95: =M69 -> 14247177 | N95: =N69 -> 19436693 | ... R95: =R69 -> 52314464
B96: 88 | D96: Dividend Valuation | G96: =G95/$F95 -> -50018519 | H96: =H95/$F95 -> -37308407 | I96: =I95/$F95 -> 2.2401834e+08 | J96: =J95/$F95 -> 2.9563619e+08 | K96: =K95/$F95 -> 3.1202704e+08 | L96: =L95/$F95 -> 3.2466456e+08 | M96: =M95/$F95 -> 3.1660393e+08 | N96: =N95/$F95 -> 4.3192651e+08 | ... R96: =R95/$F95 -> 1.1625436e+09
B97: 89 | D97: Dividend Valuation per Share | G97: =G70/$F95 -> -5.0018519 | H97: =H70/$F95 -> -3.7308407 | I97: =I70/$F95 -> 22.401834 | J97: =J70/$F95 -> 29.563619 | K97: =K70/$F95 -> 31.202704 | L97: =L70/$F95 -> 32.466456 | M97: =M70/$F95 -> 31.660393 | N97: =N70/$F95 -> 43.192651 | ... R97: =R70/$F95 -> 116.25436
B98: 90
B99: 91 | C99: Market Valuation vs. Book Value | I99: =I85/I78 -> 0.68389013 | J99: =J85/J78 -> 0.7083981 | K99: =K85/K78 -> 0.59881605 | L99: =L85/L78 -> 0.57668809 | M99: =M85/M78 -> 0.46700179 | N99: =N85/N78 -> 0.50394243 | O99: =O85/O78 -> 0.59772492 | P99: =P85/P78 -> 0.61366768 | ... R99: =R85/R78 -> 0.62651647
B100: 92 | C100: Market Valuation vs. Fair Valuation | I100: =I85/I92 -> 0.57227362 | J100: =J85/J92 -> 0.59655456 | K100: =K85/K92 -> 0.56101759 | L100: =L85/L92 -> 0.5165367 | M100: =M85/M92 -> 0.45506613 | N100: =N85/N92 -> 0.45361553 | O100: =O85/O92 -> 0.85973697 | P100: =P85/P92 -> 0.90305306 | ... R100: =R85/R92 -> 0.97319502
B101: 93 | C101: Market Valuation vs. Dividend Valuation | I101: =I85/I97 -> 0.69734273 | J101: =J85/J97 -> 0.69027286 | K101: =K85/K97 -> 0.72435326 | L101: =L85/L97 -> 0.75993526 | M101: =M85/M97 -> 0.81200122 | N101: =N85/N97 -> 0.76899907 | O101: =O85/O97 -> 0.68178477 | P101: =P85/P97 -> 0.70109488 | ... R101: =R85/R97 -> 0.74102406
B102: 94 | C102: Return on Net Tangible Equity | I102: =I95/H75 -> 0.26479509 | J102: =J95/I75 -> 0.27628912 | K102: =K95/J75 -> 0.2284806 | L102: =L95/K75 -> 0.19351904 | M102: =M95/L75 -> 0.15811598 | N102: =N95/M75 -> 0.186259 | O102: =O95/N75 -> 0.29147953 | P102: =P95/O75 -> 0.25907499 | ... R102: =R95/Q75 -> 0.21065043
B103: 95
...

Sheet INPUT_PCLP 1_250M
C1: Cash Flow and Valuation
C2: Woodfine Professional Centres Limited Partnership
C3: January 6, 2026
D5: Build Time | E5: Gross Cost per sq. ft. | F5: Portfolio additions in sf. | G5: Capital investment
C6: Phase 1 - initial funding for capital assets | D6: 3 | E6: 310 | F6: =$D$43/$E6 -> 699596.77 | G6: =+F6*E6 -> 216875000
C7: Phase 2 - first financing | D7: 2 | E7: =+E6 -> 310 | F7: =$D$48/$E7 -> 1095161.3 | G7: =+F7*E7 -> 339500000
C8: Phase 3 - second financing | D8: 2 | E8: =+E7 -> 310 | F8: =$D$49/$E8 -> 2112096.8 | G8: =+F8*E8 -> 6.5475e+08
F9: =SUM(F6:F8) -> 3906854.8 | G9: =SUM(G6:G8) -> 1211125000
C10: Development Yield | D10: 0.105
C12: Cap Rate - Public Non Listed | D12: 0.0625 | AE12: Y1 | AF12: Y2 | AG12: Y3 | AH12: Y4 | AI12: Y5 | AJ12: Y6 | AK12: Y7 | AL12: Y8 | AM12: Y9 | AN12: Y10
AA13: Revenue | AE13: - | AF13: - | AG13: - | AH13: =H57/$D45 -> 8.1978773 | AI13: =I57/$D45 -> 8.1978773 | AJ13: =J57/$D45 -> 21.030981 | AK13: =K57/$D45 -> 21.030981 | AL13: =L57/$D45 -> 45.780538 | AM13: =M57/$D45 -> 45.780538 | AN13: =N57/$D45 -> 45.780538
AA14: Distributions | AE14: - | AF14: - | AG14: - | AH14: =H122 -> 1.4416617 | AI14: =I122 -> 2.0095845 | AJ14: =J122 -> 2.8480757 | AK14: =K122 -> 4.2492987 | AL14: =L122 -> 24.091823 | AM14: =M122 -> 24.212282 | AN14: =N122 -> 24.333344
C15: Total Equity Financing - 1 year | D15: 250000000
C16: Cost per Unit | D16: 100 | AA16: Distribution Yield on Initial Capital | AE16: - | AF16: - | AG16: - | AH16: =AH14/100 -> 0.014416617 | AI16: =AI14/100 -> 0.020095845 | AJ16: =AJ14/100 -> 0.028480757 | AK16: =AK14/100 -> 0.042492987 | AL16: =AL14/100 -> 0.24091823 | AM16: =AM14/100 -> 0.24212282 | AN16: =AN14/100 -> 0.24333344
C17: Issuing Agents Fee | D17: 0.06
AA18: Asset Value | AE18: =E110 -> 100.02603 | AF18: =F110 -> 100.25224 | AG18: =G110 -> 100.17684 | AH18: =H110 -> 196.26805 | AI18: =I110 -> 259.49136 | AJ18: =J110 -> 464.41747 | AK18: =K110 -> 572.79231 | AL18: =L110 -> 733.07516 | ... AN18: =N110 -> 733.07516
C19: Advisory Fee as percentage of Gross Funded Value | D19: 0.01 | AA19: Total Debt | AE19: =E92/$D45 -> 0 | AF19: =F92/$D45 -> 0 | AG19: =G92/$D45 -> 0 | AH19: =H92/$D45 -> 63.000018 | AI19: =I92/$D45 -> 126.00004 | AJ19: =J92/$D45 -> 247.50007 | AK19: =K92/$D45 -> 355.40277 | AL19: =L92/$D45 -> 352.7259 | ... AN19: =N92/$D45 -> 347.33194
C21: Benetti Holdings Dilution | D21: 0.1 | AA21: Net Asset Value (NAV) | AE21: =E115 -> 100.02603 | AF21: =F115 -> 100.25224 | AG21: =G115 -> 100.17684 | AH21: =H115 -> 133.26804 | AI21: =I115 -> 133.49132 | AJ21: =J115 -> 216.9174 | AK21: =K115 -> 217.38954 | AL21: =L115 -> 380.34926 | ... AN21: =N115 -> 385.74322
C23: Board of Directors Expense | D23: 450000 | AA23: Market Value | AC23: 0.08 | AE23: 100 | AF23: 100 | AG23: 100 | AH23: 125.8 | AI23: 132.1 | AJ23: 171.5 | AK23: 177.3 | AL23: =AL14/AC23 -> 301.14779 | AM23: =AM14/AC23 -> 302.65353 | AN23: =AN14/AC23 -> 304.1668
C24: Admin Costs | D24: 500000 | AH24: =(AH23-AH21)/AH21 -> -0.05603771 | AI24: =(AI23-AI21)/AI21 -> -0.01042257 | AJ24: =(AJ23-AJ21)/AJ21 -> -0.20937647 | AK24: =(AK23-AK21)/AK21 -> -0.18441339 | AL24: =(AL23-AL21)/AL21 -> -0.20823353 | AM24: =(AM23-AM21)/AM21 -> -0.20986342 | AN24: =(AN23-AN21)/AN21 -> -0.21147856
C25: Discount to FMV for buildings under cost | D25: 0 | AA25: Discount / Premium vs. Net Asset Value (NAV)
C27: Issue Costs as a Percentage of Gross Funded Value | D27: 0.01 | AA27: Compounded Annual Return (Excluding Distributions) | AL27: =((AL23/100)^(1/8))-1 -> 0.14775042
C28: Issuing Agents Fee - First Secured Mortgage Debentures | D28: 0.03 | AA28: Distribution Yield to Buyers at Market Value | AL28: =AL14/AL23 -> 0.08 | AM28: =AM14/AM23 -> 0.08 | AN28: =AN14/AN23 -> 0.08
C29: Interest Paid to the First Secured Mortgage Debentures | D29: 0.05
C30: Interest earned on Cash on Hand | D30: 0.0005 | AA30: Interest Coverage Ratio | AE30: - | AF30: - | AG30: - | AH30: =H74 -> 2.0176724 | AI30: =I74 -> 1.472765 | AJ30: =J74 -> 1.3390161 | AK30: =K74 -> 1.313352 | AL30: =L74 -> 2.5064111 | AM30: =M74 -> 2.5254328 | AN30: =N74 -> 2.5448428
C31: Debenture Buy Back (% of EBITDA) | D31: 0.1 | AA31: Debt vs. Development Cost | AE31: - | AF31: - | AG31: - | AH31: =H106 -> 0.45263498 | AI31: =I106 -> 0.62907212 | AJ31: =J106 -> 0.77793494 | AK31: =K106 -> 0.81513439 | AL31: =L106 -> 0.80899485 | AM31: =M106 -> 0.80282462 | AN31: =N106 -> 0.79662353
AA32: Debt to Asset Value | AE32: - | AF32: - | AG32: - | AH32: =AH19/AH18 -> 0.32098967 | AI32: =AI19/AI18 -> 0.48556544 | AJ32: =AJ19/AJ18 -> 0.53292584 | AK32: =AK19/AK18 -> 0.62047406 | AL32: =AL19/AL18 -> 0.48115926 | AM32: =AM19/AM18 -> 0.47748944 | AN32: =AN19/AN18 -> 0.47380127
C33: Minimum cash balance | D33: 250000
C34: Working Capital Reserve during development | D34: 0.0625 | AA34: Total Expense Ratio (NAV) | AE34: =E117 -> 0.012416772 | AF34: =F117 -> 0.012388754 | AG34: =G117 -> 0.012398079 | AH34: =H117 -> 0.0093195667 | AI34: =I117 -> 0.0093039781 | AJ34: =J117 -> 0.0057256834 | AK34: =K117 -> 0.0057132479 | AL34: =L117 -> 0.0032654207 | ... AN34: =N117 -> 0.0032197594
AA35: Total Square Foot - $250 Million Gross Funded Value | AE35: - | AF35: - | AG35: - | AH35: =+F6 -> 699596.77 | AI35: =AH35 -> 699596.77 | AJ35: =+AI35+F7 -> 1794758.1 | AK35: =AJ35 -> 1794758.1 | AL35: =(D43+D48+D49)/E6 -> 3906854.8 | AM35: =AL35 -> 3906854.8 | AN35: =AM35 -> 3906854.8
C37: Equity Proceeds
C38: Partner Contributions | D38: =D15-D32 -> 250000000 | AA38: Year 8 | AE38: $ | AF38: %
C39: Issuing Agents Fees | D39: =D17*D38 -> 15000000
C40: Issue Costs | D40: =+D27*D38 -> 2500000 | AA40: Revenue | AE40: =AL13 -> 45.780538 | AF40: =AE40/AE40 -> 1
C41: Net Proceeds | D41: =D38-D39-D40 -> 232500000
C42: Working Capital | D42: =D34*D38 -> 15625000 | AB42: Advisory Fee | AE42: =L63/D45 -> 0.90000025 | AF42: =AE42/AE40 -> 0.019659014
C43: Net Equity Funding | D43: =D41-D42 -> 216875000
AB44: Operating and Administrative Expense | AE44: =(L64+L65)/D45 -> 0.3420001 | AF44: =AE44/AE40 -> 0.0074704255
C45: Number of Diluted Units | D45: =ROUND(+((D38/D16)/(1-D21)),0)-1 -> 2777777 | E45: =D45*100 -> 277777700 | AB45: Interest Payments | AE45: =(L69/D45)*-1 -> 17.769845 | AF45: =AE45/AE40 -> 0.38815283
C47: Debt Proceeds | E47: Gross borrowing | AA47: Distributable Income
C48: Initial Financing (net of 3% cost) | D48: =+E48-E48*0.03 -> 339500000 | E48: 350000000
C49: Secondary Financing (net of 3% cost) | D49: =+E49-E49*0.03 -> 654750000 | E49: 675000000 | AB49: Repurchase Of Debentures | AE49: =(L83/D45)*-1 -> 2.6768692 | AF49: =AE49/AE40 -> 0.058471773
C50: Total (max) Debt Financing | E50: =SUM(E48:E49) -> 1025000000 | AB50: Distributions | AE50: =(L84/D45)*-1 -> 24.091823 | AF50: =AE50/AE40 -> 0.52624596
E55: 1 | F55: 2 | G55: 3 | H55: 4 | I55: 5 | J55: 6 | K55: 7 | L55: 8 | M55: 9 | N55: 10 | O55: 11 | P55: 12 | Q55: 13 | R55: 14 | S55: 15 | T55: 16 | U55: 17 | V55: 18 | W55: 19 | X55: 20
C56: Income
C57: Net proceeds from operations | E57: =E102*$D$10 -> 0 | F57: =F102*$D$10 -> 0 | G57: =G102*$D$10 -> 0 | H57: =H102*$D$10 -> 22771875 | I57: =I102*$D$10 -> 22771875 | J57: =J102*$D$10 -> 58419375 | K57: =K102*$D$10 -> 58419375 | L57: =L102*$D$10 -> 127168125 | ... X57: =X102*$D$10 -> 127168125
C58: Income Continuity | D58: (Note-1) | E58: 3050000 | F58: 3300000 | G58: 3500000 | H58: =SUM(H57:H57) -> 22771875 | I58: =SUM(I57:I57) -> 22771875 | J58: =SUM(J57:J57) -> 58419375 | K58: =SUM(K57:K57) -> 58419375 | L58: =SUM(L57:L57) -> 127168125 | M58: =SUM(M57:M57) -> 127168125 | N58: =SUM(N57:N57) -> 127168125 | O58: =SUM(O57:O57) -> 127168125 | ... X58: =SUM(X57:X57) -> 127168125
C60: Expenses & Fees
C61: Issue Costs | E61: =$D27*$D15 -> 2500000 | F61: 0 | G61: 0 | H61: 0 | I61: 0 | J61: 0 | K61: 0 | L61: 0 | M61: 0 | N61: 0 | O61: 0 | P61: 0 | Q61: 0 | R61: 0 | S61: 0 | T61: 0 | U61: 0 | V61: 0 | W61: 0 | X61: 0
C62: Financing costs | E62: =D39 -> 15000000 | F62: 0 | G62: 0 | H62: =D28*E48 -> 10500000 | I62: 0 | J62: =D28*E49 -> 20250000 | K62: 0 | L62: 0 | M62: 0 | N62: 0 | O62: 0 | P62: 0 | Q62: 0 | R62: 0 | S62: 0 | T62: 0 | U62: 0 | V62: 0 | W62: 0 | X62: 0
C63: Advisory Fees | E63: =$D19*$D15 -> 2500000 | F63: =$D19*$D15 -> 2500000 | G63: =$D19*$D15 -> 2500000 | H63: =$D19*$D15 -> 2500000 | I63: =$D19*$D15 -> 2500000 | J63: =$D19*$D15 -> 2500000 | K63: =$D19*$D15 -> 2500000 | L63: =$D19*$D15 -> 2500000 | ... X63: =$D19*$D15 -> 2500000
C64: Admin and Compliance | E64: =$D24 -> 500000 | F64: =$D24 -> 500000 | G64: =$D24 -> 500000 | H64: =$D24 -> 500000 | I64: =$D24 -> 500000 | J64: =$D24 -> 500000 | K64: =$D24 -> 500000 | L64: =$D24 -> 500000 | ... X64: =$D24 -> 500000
C65: Board of Directors | E65: =+$D23 -> 450000 | F65: =+$D23 -> 450000 | G65: =+$D23 -> 450000 | H65: =+$D23 -> 450000 | I65: =+$D23 -> 450000 | J65: =+$D23 -> 450000 | K65: =+$D23 -> 450000 | L65: =+$D23 -> 450000 | ... X65: =+$D23 -> 450000
C66: Total Expenses | E66: =SUM(E61:E65) -> 20950000 | F66: =SUM(F61:F65) -> 3450000 | G66: =SUM(G61:G65) -> 3450000 | H66: =SUM(H61:H65) -> 13950000 | I66: =SUM(I61:I65) -> 3450000 | J66: =SUM(J61:J65) -> 23700000 | K66: =SUM(K61:K65) -> 3450000 | L66: =SUM(L61:L65) -> 3450000 | ... X66: =SUM(X61:X65) -> 3450000
C68: Earnings before interest, taxes and depreciation (EBITDA) | E68: =+E57-E66 -> -20950000 | F68: =+F57-F66 -> -3450000 | G68: =+G57-G66 -> -3450000 | H68: =+H58-H66 -> 8821875 | I68: =+I58-I66 -> 19321875 | J68: =+J58-J66 -> 34719375 | K68: =+K58-K66 -> 54969375 | L68: =+L58-L66 -> 123718125 | M68: =+M58-M66 -> 123718125 | N68: =+N58-N66 -> 123718125 | O68: =+O58-O66 -> 123718125 | ... X68: =+X58-X66 -> 123718125
C69: Cost of Debenture Debt net of interest on funds on deposit | E69: =(SUM(E79)*$D$30)-((E89+E92)/2*$D$29) -> 0 | F69: =(SUM(F79)*$D$30)-((F89+F92)/2*$D$29) -> 78379.167 | G69: =(SUM(G79)*$D$30)-((G89+G92)/2*$D$29) -> 40547.523 | H69: =(SUM(H79)*$D$30)-((H89+H92)/2*$D$29) -> -4372303 | I69: =(SUM(I79)*$D$30)-((I89+I92)/2*$D$29) -> -13119456 | J69: =(SUM(J79)*$D$30)-((J89+J92)/2*$D$29) -> -25929020 | K69: =(SUM(K79)*$D$30)-((K89+K92)/2*$D$29) -> -41854259 | L69: =(SUM(L79)*$D$30)-(L89*$D$29) -> -49360667 | M69: =(SUM(M79)*$D$30)-(M89*$D$29) -> -48988880 | N69: =(SUM(N79)*$D$30)-(N89*$D$29) -> -48615234 | O69: =(SUM(O79)*$D$30)-(O89*$D$29) -> -48239719 | P69: =(SUM(P79)*$D$30)-(P89*$D$29) -> -47862327 | Q69: =(SUM(Q79)*$D$30)-(Q89*$D$29) -> -47483048 | R69: =(SUM(R79)*$D$30)-(R89*$D$29) -> -47101873 | S69: =(SUM(S79)*$D$30)-(S89*$D$29) -> -46718792 | ... X69: =(SUM(X79)*$D$30)-(X89*$D$29) -> -44774462
C70: Percentage Interest Payable - net of interest income | H70: =(H69/H92)*-1 -> 0.024984589 | I70: =(I69/I92)*-1 -> 0.037484159 | J70: =(J69/J92)*-1 -> 0.037714939 | K70: =(K69/K92)*-1 -> 0.042395667 | L70: =(L69/L92)*-1 -> 0.050378623 | M70: =(M69/M92)*-1 -> 0.050383445 | N70: =(N69/N92)*-1 -> 0.050388366 | O70: =(O69/O92)*-1 -> 0.05039339 | ... X70: =(X69/X92)*-1 -> 0.050443779
C72: Funding from operations | E72: =SUM(E68:E69) -> -20950000 | F72: =SUM(F68:F69) -> -3371620.8 | G72: =SUM(G68:G69) -> -3409452.5 | H72: =SUM(H68:H69) -> 4449572 | I72: =SUM(I68:I69) -> 6202419.4 | J72: =SUM(J68:J69) -> 8790354.6 | K72: =SUM(K68:K69) -> 13115116 | L72: =SUM(L68:L69) -> 74357458 | ... X72: =SUM(X68:X69) -> 78943663
C74: Interest Coverage Ratio | E74: n/a | F74: n/a | G74: n/a | H74: =H68/H69*-1 -> 2.0176724 | I74: =I68/I69*-1 -> 1.472765 | J74: =J68/J69*-1 -> 1.3390161 | K74: =K68/K69*-1 -> 1.313352 | L74: =L68/L69*-1 -> 2.5064111 | M74: =M68/M69*-1 -> 2.5254328 | N74: =N68/N69*-1 -> 2.5448428 | O74: =O68/O69*-1 -> 2.5646527 | ... X74: =X68/X69*-1 -> 2.7631404
C75: Debt Service Ratio | E75: n/a | F75: n/a | G75: n/a | H75: =+H68/(-H69-H91) -> 2.0176724 | I75: =+I68/(-I69-I91) -> 1.472765 | J75: =+J68/(-J69-J91) -> 1.3390161 | K75: =+K68/(-K69-K91) -> 1.313352 | L75: =+L68/(-L69-L91) -> 2.1782736 | M75: =+M68/(-M69-M91) -> 2.1911826 | N75: =+N68/(-N69-N91) -> 2.2043113 | O75: =+O68/(-O69-O91) -> 2.2176651 | ... X75: =+X68/(-X69-X91) -> 2.3489819
C76: Proceeds as a % of EBITDA | E76: n/a | F76: n/a | G76: n/a | H76: =H68/H58 -> 0.38740222 | I76: =I68/I58 -> 0.84849732 | J76: =J68/J58 -> 0.59431267 | K76: =K68/K58 -> 0.94094425 | L76: =L68/L58 -> 0.97287056 | M76: =M68/M58 -> 0.97287056 | N76: =N68/N58 -> 0.97287056 | O76: =O68/O58 -> 0.97287056 | ... X76: =X68/X58 -> 0.97287056
C78: Cash Flow Continuity
C79: Opening Cash | E79: 0 | F79: =E86 -> 1.5675833e+08 | G79: =F86 -> 81095046 | H79: =G86 -> 5393926.7 | I79: =H86 -> 11088884 | J79: =I86 -> 16959126 | K79: =J86 -> 27963161 | L79: =K86 -> 1629309.9 | M79: =L86 -> 1629309.9 | ... X79: =W86 -> 1629354.9
C80: New Equity Financing | E80: =$D$38 -> 250000000 | F80: 0 | G80: 0 | H80: 0 | I80: 0 | J80: 0 | K80: 0 | L80: 0 | M80: 0 | N80: 0 | O80: 1 | P80: 2 | Q80: 3 | R80: 4 | S80: 5 | T80: 6 | U80: 7 | V80: 8 | W80: 9 | X80: 10
C81: New Debt Financing (gross) | E81: =E90 -> 0 | F81: =F90 -> 0 | G81: =G90 -> 0 | H81: =H90 -> 175000000 | I81: =I90 -> 175000000 | J81: =J90 -> 337500000 | K81: =K90 -> 2.9972964e+08 | L81: =L90 -> 0 | ... X81: =X90 -> 0
C82: Capital Asset Additions | E82: =-E100+E96 -> -72291667 | F82: =-F100+F96 -> -72291667 | G82: =-G100+G96 -> -72291667 | H82: =-H100+H96 -> -169750000 | I82: =-I100+I96 -> -169750000 | J82: =-J100+J96 -> -327375000 | K82: =-K100+K96 -> -327375000 | L82: =-L100+L96 -> 0 | ... X82: =-X100+X96 -> 0
C83: Debt Repayment | E83: =E91 -> 0 | F83: =F91 -> 0 | G83: =G91 -> 0 | H83: =H91 -> 0 | I83: =I91 -> 0 | J83: =J91 -> 0 | K83: =K91 -> 0 | L83: =L91 -> -7435745.8 | ... X83: =X91 -> -7894366.3
C84: Distributions | E84: =-E120 -> 0 | F84: =-F120 -> 0 | G84: =-G120 -> 0 | H84: =-H120 -> -4004614.8 | I84: =-I120 -> -5582177.5 | J84: =-J120 -> -7911319.1 | K84: =-K120 -> -11803604 | L84: =-L120 -> -66921712 | ... X84: =-X120 -> -71049297
C85: =+C72 -> Funding from operations | E85: =E72 -> -20950000 | F85: =F72 -> -3371620.8 | G85: =G72 -> -3409452.5 | H85: =H72 -> 4449572 | I85: =I72 -> 6202419.4 | J85: =J72 -> 8790354.6 | K85: =K72 -> 13115116 | L85: =L72 -> 74357458 | ... X85: =X72 -> 78943663
C86: Ending Cash | E86: =SUM(E79:E85) -> 1.5675833e+08 | F86: =SUM(F79:F85) -> 81095046 | G86: =SUM(G79:G85) -> 5393926.7 | H86: =SUM(H79:H85) -> 11088884 | I86: =SUM(I79:I85) -> 16959126 | J86: =SUM(J79:J85) -> 27963161 | K86: =SUM(K79:K85) -> 1629309.9 | L86: =SUM(L79:L85) -> 1629309.9 | ... X86: =SUM(X79:X85) -> 1629364.9
C88: Debenture Continuity
C89: Opening Debt | E89: 0 | F89: =E92 -> 0 | G89: =F92 -> 0 | H89: =G92 -> 0 | I89: =H92 -> 175000000 | J89: =I92 -> 350000000 | K89: =J92 -> 687500000 | L89: =K92 -> 987229637 | M89: =L92 -> 9.7979389e+08 | ... X89: =W92 -> 8.9550553e+08
C90: Additions | E90: 0 | F90: 0 | G90: 0 | H90: =+E48/2 -> 175000000 | I90: =+E48/2 -> 175000000 | J90: =+E49/2 -> 337500000 | K90: =SUM(K97:K99)-ROUND(J86,)+D33-816+(80201-12030+443) -> 2.9972964e+08 | L90: 0 | M90: =SUM(M97:M99) -> 0 | N90: =SUM(N97:N99) -> 0 | O90: =SUM(O97:O99) -> 0 | P90: =SUM(P97:P99) -> 0 | Q90: =SUM(Q97:Q99) -> 0 | R90: =SUM(R97:R99) -> 0 | S90: =SUM(S97:S99) -> 0 | T90: =SUM(T97:T99) -> 0 | ... X90: =SUM(X97:X99) -> 0
C91: Payments | E91: 0 | F91: 0 | G91: 0 | H91: 0 | L91: =-L72*$D31 -> -7435745.8 | M91: =-M72*$D31 -> -7472924.5 | N91: =-N72*$D31 -> -7510289.1 | O91: =-O72*$D31 -> -7547840.6 | P91: =-P72*$D31 -> -7585579.8 | Q91: =-Q72*$D31 -> -7623507.7 | R91: =-R72*$D31 -> -7661625.2 | S91: =-S72*$D31 -> -7699933.3 | ... X91: =-X72*$D31 -> -7894366.3
C92: Ending Debt | E92: =SUM(E89:E91) -> 0 | F92: =SUM(F89:F91) -> 0 | G92: =SUM(G89:G91) -> 0 | H92: =SUM(H89:H91) -> 175000000 | I92: =SUM(I89:I91) -> 350000000 | J92: =SUM(J89:J91) -> 687500000 | K92: =SUM(K89:K91) -> 987229637 | L92: =SUM(L89:L91) -> 9.7979389e+08 | ... X92: =SUM(X89:X91) -> 8.8761116e+08
C95: Asset Continuity
C96: Opening Assets | E96: 0 | F96: =E100 -> 72291667 | G96: =F100 -> 1.4458333e+08 | H96: =G100 -> 216875000 | I96: =H100 -> 386625000 | J96: =I100 -> 556375000 | K96: =J100 -> 883750000 | L96: =K100 -> 1211125000 | M96: =L100 -> 1211125000 | ... X96: =W100 -> 1211125000
C97: =+C6 -> Phase 1 - initial funding for capital assets | E97: =($F$6*$E$6)/$D6 -> 72291667 | F97: =($F$6*$E$6)/$D6 -> 72291667 | G97: =($F$6*$E$6)/$D6 -> 72291667 | H97: 0 | I97: 0 | J97: 0 | K97: 0 | L97: 0 | M97: 0 | N97: 0 | O97: 0 | P97: 0 | Q97: 0 | R97: 0 | S97: 0 | T97: 0 | U97: 0 | V97: 0 | W97: 0 | X97: 0
C98: =+C7 -> Phase 2 - first financing | E98: 0 | F98: 0 | G98: 0 | H98: =($F$7*$E$7)/$D7 -> 169750000 | I98: =($F$7*$E$7)/$D7 -> 169750000 | J98: 0 | K98: 0 | L98: 0 | M98: 0 | N98: 0 | O98: 0 | P98: 0 | Q98: 0 | R98: 0 | S98: 0 | T98: 0 | U98: 0 | V98: 0 | W98: 0 | X98: 0
C99: =+C8 -> Phase 3 - second financing | E99: 0 | F99: 0 | G99: 0 | H99: 0 | I99: 0 | J99: =($F8*$E8)/$D8 -> 3.27375e+08 | K99: =($F8*$E8)/$D8 -> 3.27375e+08 | L99: 0 | M99: 0 | N99: 0 | O99: 0 | P99: 0 | Q99: 0 | R99: 0 | S99: 0 | T99: 0 | U99: 0 | V99: 0 | W99: 0 | X99: 0
C100: Total Capital Assets | E100: =SUM(E96:E99) -> 72291667 | F100: =SUM(F96:F99) -> 1.4458333e+08 | G100: =SUM(G96:G99) -> 216875000 | H100: =SUM(H96:H99) -> 386625000 | I100: =SUM(I96:I99) -> 556375000 | J100: =SUM(J96:J99) -> 883750000 | K100: =SUM(K96:K99) -> 1211125000 | L100: =SUM(L96:L99) -> 1211125000 | ... X100: =SUM(X96:X99) -> 1211125000
C102: Total Capital Assets Generating Rent | E102: 0 | F102: 0 | G102: 0 | H102: =G100 -> 216875000 | I102: =H102 -> 216875000 | J102: =I100 -> 556375000 | K102: =J102 -> 556375000 | L102: =K100 -> 1211125000 | M102: =L102 -> 1211125000 | N102: =M102 -> 1211125000 | O102: =N102 -> 1211125000 | P102: =O102 -> 1211125000 | Q102: =P102 -> 1211125000 | R102: =Q102 -> 1211125000 | S102: =R102 -> 1211125000 | T102: =S102 -> 1211125000 | ... X102: =W102 -> 1211125000
C104: Buildings under construction | E104: =E100-E102 -> 72291667 | F104: =F100-F102 -> 1.4458333e+08 | G104: =G100-G102 -> 216875000 | H104: =H100-H102 -> 169750000 | I104: =I100-I102 -> 339500000 | J104: =J100-J102 -> 327375000 | K104: =K100-K102 -> 654750000 | L104: =L100-L102 -> 0 | ... X104: =X100-X102 -> 0
C105: FMV of building under construction | E105: =E104*(1-$D$25) -> 72291667 | F105: =F104*(1-$D$25) -> 1.4458333e+08 | G105: =G104*(1-$D$25) -> 216875000 | H105: =H104*(1-$D$25) -> 169750000 | I105: =I104*(1-$D$25) -> 339500000 | J105: =J104*(1-$D$25) -> 327375000 | K105: =K104*(1-$D$25) -> 654750000 | L105: =L104*(1-$D$25) -> 0 | ... X105: =X104*(1-$D$25) -> 0
C106: Debt to development cost | E106: =E92/E100 -> 0 | F106: =F92/F100 -> 0 | G106: =G92/G100 -> 0 | H106: =H92/H100 -> 0.45263498 | I106: =I92/I100 -> 0.62907212 | J106: =J92/J100 -> 0.77793494 | K106: =K92/K100 -> 0.81513439 | L106: =L92/L100 -> 0.80899485 | ... X106: =X92/X100 -> 0.73288155
C108: Asset Valuation
C109: Cap Rate - Public Non Listed | E109: =(E58/$D12)+$E104+$E86 -> 277850000 | F109: =(F58/$D12)+$F105+$F86 -> 2.7847838e+08 | G109: =(G58/$D12)+$G104+$G86 -> 2.7826893e+08 | H109: =(H58/$D12)+$H104+$H86 -> 5.4518888e+08 | I109: =(I58/$D12)+$I104+$I86 -> 7.2080913e+08 | J109: =(J58/$D12)+$J104+$J86 -> 1.2900482e+09 | K109: =(K58/$D12)+$K104+$K86 -> 1.5910893e+09 | L109: =(L58/$D12)+$L104+$L86 -> 2.0363193e+09 | M109: =(M58/$D12)+$M104+$M86 -> 2.0363193e+09 | N109: =(N58/$D12)+$N104+$N86 -> 2.0363193e+09 | O109: =(O58/$D12)+$H104+$H86 -> 2.2155289e+09 | P109: =(P58/$D12)+$H104+$H86 -> 2.2155289e+09 | Q109: =(Q58/$D12)+$H104+$H86 -> 2.2155289e+09 | R109: =(R58/$D12)+$H104+$H86 -> 2.2155289e+09 | S109: =(S58/$D12)+$H104+$H86 -> 2.2155289e+09 | T109: =(T58/$D12)+$H104+$H86 -> 2.2155289e+09 | U109: =(U58/$D12)+$H104+$H86 -> 2.2155289e+09 | V109: =(V58/$D12)+$H104+$H86 -> 2.2155289e+09 | ... X109: =(X58/$D12)+$H104+$H86 -> 2.2155289e+09
C110: Asset Valuation (per diluted Unit) | E110: =+E109/$D$45 -> 100.02603 | F110: =+F109/$D$45 -> 100.25224 | G110: =+G109/$D$45 -> 100.17684 | H110: =+H109/$D$45 -> 196.26805 | I110: =+I109/$D$45 -> 259.49136 | J110: =+J109/$D$45 -> 464.41747 | K110: =+K109/$D$45 -> 572.79231 | L110: =L109/$D$45 -> 733.07516 | M110: =M109/$D$45 -> 733.07516 | N110: =N109/$D$45 -> 733.07516 | O110: =O109/$D$45 -> 797.59062 | P110: =P109/$D$45 -> 797.59062 | Q110: =Q109/$D$45 -> 797.59062 | R110: =R109/$D$45 -> 797.59062 | S110: =S109/$D$45 -> 797.59062 | ... X110: =X109/$D$45 -> 797.59062
C112: Net Asset Valuations
C114: Cap Rate - Public Non Listed | E114: =E109-E92 -> 277850000 | F114: =F109-F92 -> 2.7847838e+08 | G114: =G109-G92 -> 2.7826893e+08 | H114: =H109-H92 -> 3.7018888e+08 | I114: =I109-I92 -> 3.7080913e+08 | J114: =J109-J92 -> 6.0254816e+08 | K114: =K109-K92 -> 6.0385967e+08 | L114: =L109-L92 -> 1.0565254e+09 | ... X114: =X109-X92 -> 1.3279177e+09
C115: Asset Valuation (per diluted Unit) | E115: =E114/$D45 -> 100.02603 | F115: =F114/$D45 -> 100.25224 | G115: =G114/$D45 -> 100.17684 | H115: =H114/$D45 -> 133.26804 | I115: =I114/$D45 -> 133.49132 | J115: =J114/$D45 -> 216.9174 | K115: =K114/$D45 -> 217.38954 | L115: =L114/$D45 -> 380.34926 | ... X115: =X114/$D45 -> 478.05051
C116: Distribution Yield | E116: =E122/E115 -> 0 | F116: =F122/F115 -> 0 | G116: =G122/G115 -> 0 | H116: =H122/H115 -> 0.010817761 | I116: =I122/I115 -> 0.015054046 | J116: =J122/J115 -> 0.013129771 | K116: =K122/K115 -> 0.019546932 | L116: =L122/L115 -> 0.063341318 | ... X116: =X122/X115 -> 0.053504292
C117: Total Expense Ratio vs NAV ( excluding financing costs ) | E117: =SUM(E63:E65)/E114 -> 0.012416772 | F117: =SUM(F63:F65)/F114 -> 0.012388754 | G117: =SUM(G63:G65)/G114 -> 0.012398079 | H117: =SUM(H63:H65)/H114 -> 0.0093195667 | I117: =SUM(I63:I65)/I114 -> 0.0093039781 | J117: =SUM(J63:J65)/J114 -> 0.0057256834 | K117: =SUM(K63:K65)/K114 -> 0.0057132479 | L117: =SUM(L63:L65)/L114 -> 0.0032654207 | ... X117: =SUM(X63:X65)/X114 -> 0.0025980525
C119: Distribution Analysis
C120: Distribution to Limited Partners | E120: 0 | F120: 0 | G120: 0 | H120: =+H72*0.9+H91 -> 4004614.8 | I120: =+I72*0.9+I91 -> 5582177.5 | J120: =+J72*0.9+J91 -> 7911319.1 | K120: =+K72*0.9+K91 -> 11803604 | L120: =+L72+L91+L90 -> 66921712 | M120: =+M72+M91 -> 67256321 | N120: =+N72+N91 -> 67592602 | O120: =+O72+O91 -> 67930565 | P120: =+P72+P91 -> 68270218 | Q120: =+Q72+Q91 -> 68611569 | R120: =+R72+R91 -> 68954627 | S120: =+S72+S91 -> 69299400 | T120: =+T72+T91 -> 69645897 | ... X120: =+X72+X91 -> 71049297
C122: Distribution per Diluted Unit | E122: 0 | F122: 0 | G122: 0 | H122: =H120/$D45 -> 1.4416617 | I122: =I120/$D45 -> 2.0095845 | J122: =J120/$D45 -> 2.8480757 | K122: =K120/$D45 -> 4.2492987 | L122: =L120/$D45 -> 24.091823 | M122: =M120/$D45 -> 24.212282 | N122: =N120/$D45 -> 24.333344 | O122: =O120/$D45 -> 24.45501 | ... X122: =X120/$D45 -> 25.577754
C123: Distribution Yield (on original $100 investment) | E123: =E122/$D16 -> 0 | F123: =F122/$D16 -> 0 | G123: =G122/$D16 -> 0 | H123: =H122/$D16 -> 0.014416617 | I123: =I122/$D16 -> 0.020095845 | J123: =J122/$D16 -> 0.028480757 | K123: =K122/$D16 -> 0.042492987 | L123: =L122/$D16 -> 0.24091823 | ... X123: =X122/$D16 -> 0.25577754
C125: Distribution year over year growth | E125: 0 | F125: 0 | G125: 0 | H125: 0 | I125: =(I122-H122)/H122 -> 0.3939362 | J125: =(J122-I122)/I122 -> 0.41724607 | K125: =(K122-J122)/J122 -> 0.49198938 | L125: =(L122-K122)/K122 -> 4.6695999 | M125: =(M122-L122)/L122 -> 0.005 | N125: =(N122-M122)/M122 -> 0.005 | O125: =(O122-N122)/N122 -> 0.005 | P125: =(P122-O122)/O122 -> 0.005 | ... S125: =(S122-R122)/R122 -> 0.005 | T125: =+(T122-S122)/S122 -> 0.005 | U125: =+(U122-T122)/T122 -> 0.005 | V125: =+(V122-U122)/U122 -> 0.005 | W125: =+(W122-V122)/V122 -> 0.0050000001 | X125: =+(X122-W122)/W122 -> 0.0050000001
C127: Earnings Before Taxes, Depreciation and Interest on the Debt | E127: =E68/$D$45 -> -7.5420021 | F127: =F68/$D$45 -> -1.2420003 | G127: =G68/$D$45 -> -1.2420003 | H127: =H68/$D$45 -> 3.1758759 | I127: =I68/$D$45 -> 6.9558769 | J127: =J68/$D$45 -> 12.498978 | K127: =K68/$D$45 -> 19.788981 | L127: =L68/$D$45 -> 44.538537 | ... X127: =X68/$D$45 -> 44.538537
B130: Note-1:
...
