Workbook

Sheet Alert

Sheet SPV_Compensations
C2: SPV Arrangements - Asset Manager Dilution
C3: Compensations
C4: Woodfine Management Corp.
C5: Jennifer M. Woodfine
C6: January 6, 2026
C7: V3
I8: 0.1 | K8: 0.15 | M8: 2/20
C10: Management Fee | I10: ='SPV_Compensations_10 percent'!AL7 -> 800000 | K10: ='SPV_Compensations_15 percent'!AL7 -> 800000 | M10: ='SPV_Compensations_2&20'!Z7 -> 2693097.5 | N10: *
C11: Management Carry | I11: ='SPV_Compensations_10 percent'!AL8 -> 2860705.9 | K11: ='SPV_Compensations_15 percent'!AL8 -> 4291226.2 | M11: ='SPV_Compensations_2&20'!Z8 -> 7454845.4
C12: Distributions | I12: ='SPV_Compensations_10 percent'!AL9 -> 240670.7 | K12: ='SPV_Compensations_15 percent'!AL9 -> 361006.05 | M12: 0
I13: =SUM(I10:I12) -> 3901376.6 | K13: =SUM(K10:K12) -> 5452232.2 | M13: =SUM(M10:M12) -> 10147943 | N13: †
C15: Board of Directors Expense | I15: ='SPV_Compensations_10 percent'!AC8 -> 50000 | K15: ='SPV_Compensations_15 percent'!AC8 -> 50000 | M15: ='SPV_Compensations_2&20'!Q8 -> 30000
C16: Admin Costs | I16: ='SPV_Compensations_10 percent'!AC9 -> 20000 | K16: ='SPV_Compensations_15 percent'!AC9 -> 20000 | M16: ='SPV_Compensations_2&20'!Q9 -> 20000
C17: Working Capital Reserve | I17: ='SPV_Compensations_10 percent'!AC10 -> 0.051 | K17: ='SPV_Compensations_15 percent'!AC10 -> 0.051 | M17: ='SPV_Compensations_2&20'!Q10 -> 0.02
C18: Minimum Cash Position | I18: ='SPV_Compensations_10 percent'!AC11 -> 4463.0538 | K18: ='SPV_Compensations_15 percent'!AC11 -> 4463.0538 | M18: 0
C20: Distribution Yield on Initial Capital | I20: ='SPV_Compensations_10 percent'!AL16 -> 0.19054206 | K20: ='SPV_Compensations_15 percent'!AL16 -> 0.17995621 | M20: ='SPV_Compensations_2&20'!Z16 -> 0.15943835
C21: Market Value | I21: ='SPV_Compensations_10 percent'!AL23 -> 257.48928 | K21: ='SPV_Compensations_15 percent'!AL23 -> 243.18407 | M21: ='SPV_Compensations_2&20'!Z23 -> 229.4077
C23: Discount / Premium vs. Net Asset Value (NAV) | I23: ='SPV_Compensations_10 percent'!AL24 -> -0.20825892 | K23: ='SPV_Compensations_15 percent'!AL24 -> -0.20825892 | M23: ='SPV_Compensations_2&20'!Z24 -> -0.21051812
C25: Compounded Annual Return (Excluding Distributions) | I25: ='SPV_Compensations_10 percent'!AL27 -> 0.12549843 | K25: ='SPV_Compensations_15 percent'!AL27 -> 0.11748549 | M25: ='SPV_Compensations_2&20'!Z27 -> 0.10936893
C26: Distribution Yield to Buyers at Market Value | I26: ='SPV_Compensations_10 percent'!AL28 -> 0.074 | K26: ='SPV_Compensations_15 percent'!AL28 -> 0.074 | M26: ='SPV_Compensations_2&20'!Z28 -> 0.0695
C28: *In the case of the 2/20, the Management Fee calculated on the NAV is accrued rather than distributed due to the size of the Working Capital Reserve that would be required.
C31: † Final Sale must occur
C33: NTD - The pro forma figures above represent preliminary, high-level estimates based on current assumptions and are subject to change

Sheet SPV_Compensations_10 percent
C1: Cash Flow and Valuation
C2: Woodfine Professional Centres Limited Partnership
C3: January 6, 2026
D5: Build Time | E5: Gross Cost per sq. ft. | F5: Portfolio additions in sf. | G5: Capital investment
C6: Phase 1 - initial funding for capital assets | D6: 1 | E6: 310 | F6: =$D$43/$E6 -> 30612.903 | G6: =+F6*E6 -> 9490000 | AA6: SPV Arrangements - Asset Manager Dilution
C7: Phase 2 - first financing | D7: 2 | E7: =+E6 -> 310 | F7: =$D$48/$E7 -> 0 | G7: =+F7*E7 -> 0 | AA7: Unit-based Compensation | AC7: =D21 -> 0.1 | AI7: Management Fee (1% GFV) | AL7: =SUM(E63:L63) -> 800000
C8: Phase 3 - second financing | D8: 2 | E8: =+E7 -> 310 | F8: =$D$49/$E8 -> 0 | G8: =+F8*E8 -> 0 | AA8: =C23 -> Board of Directors Expense | AC8: =D23 -> 50000 | AI8: Unit-based Compenstion (10% Market Value) | AL8: =AL23*(D45-100000) -> 2860705.9
F9: =SUM(F6:F8) -> 30612.903 | G9: =SUM(G6:G8) -> 9490000 | AA9: =C24 -> Admin Costs | AC9: =D24 -> 20000 | AI9: Distributions | AL9: =SUM(E120:L120)*AC7 -> 240670.7
C10: Development Yield | D10: 0.105 | AA10: Working Capital Reserve | AC10: =D34 -> 0.051
AA11: Minimum Cash Position | AC11: =H86 -> 4463.0538
C12: Cap Rate - Public Non Listed | D12: 0.0625 | AE12: Y1 | AF12: Y2 | AG12: Y3 | AH12: Y4 | AI12: Y5 | AJ12: Y6 | AK12: Y7 | AL12: Y8 | AM12: Y9 | AN12: Y10
AA13: Revenue | AE13: - | AF13: - | AG13: - | AH13: =H57/$D45 -> 1.2313356 | AI13: =I57/$D45 -> 1.7164033 | AJ13: =J57/$D45 -> 2.4325658 | AK13: =K57/$D45 -> 3.6293623 | AL13: =L57/$D45 -> 20.577032 | AM13: =M57/$D45 -> 20.679917 | AN13: =N57/$D45 -> 20.783317
AA14: Distributions | AE14: - | AF14: - | AG14: - | AH14: =H122 -> -0.26755361 | AI14: =I122 -> 0.16847218 | AJ14: =J122 -> 0.81335538 | AK14: =K122 -> 1.892099 | AL14: =L122 -> 19.054206 | AM14: =M122 -> 19.157092 | AN14: =N122 -> 19.260491
C15: Total Equity Financing - 1 year | D15: 10000000
C16: Cost per Unit | D16: 100 | AA16: Distribution Yield on Initial Capital | AE16: - | AF16: - | AG16: - | AH16: =AH14/100 -> -0.0026755361 | AI16: =AI14/100 -> 0.0016847218 | AJ16: =AJ14/100 -> 0.0081335538 | AK16: =AK14/100 -> 0.01892099 | AL16: =AL14/100 -> 0.19054206 | AM16: =AM14/100 -> 0.19157092 | AN16: =AN14/100 -> 0.19260491
C17: Issuing Agents Fee | D17: 0
AA18: Asset Value | AE18: =E110 -> 88.470885 | AF18: =F110 -> 87.194839 | AG18: =G110 -> 85.631792 | AH18: =H110 -> 113.86554 | AI18: =I110 -> 114.07497 | AJ18: =J110 -> 185.42026 | AK18: =K110 -> 186.03376 | AL18: =L110 -> 325.21904 | ... AN18: =N110 -> 329.82607
C19: Advisory Fee as percentage of Gross Funded Value | D19: 0.01 | AA19: Total Debt | AE19: =E92/$D45 -> 0 | AF19: =F92/$D45 -> 0 | AG19: =G92/$D45 -> 0 | AH19: =H92/$D45 -> 0 | AI19: =I92/$D45 -> 0 | AJ19: =J92/$D45 -> 0 | AK19: =K92/$D45 -> 0 | AL19: =L92/$D45 -> 0 | ... AN19: =N92/$D45 -> 0
C21: Benetti Holdings Dilution | D21: 0.1 | AA21: Net Asset Value (NAV) | AE21: =E115 -> 88.470885 | AF21: =F115 -> 87.194839 | AG21: =G115 -> 85.631792 | AH21: =H115 -> 113.86554 | AI21: =I115 -> 114.07497 | AJ21: =J115 -> 185.42026 | AK21: =K115 -> 186.03376 | AL21: =L115 -> 325.21904 | ... AN21: =N115 -> 329.82607
C23: Board of Directors Expense | D23: 50000 | AA23: Market Value | AC23: 0.074 | AE23: 100 | AF23: 100 | AG23: 100 | AH23: 125.8 | AI23: 132.1 | AJ23: 171.5 | AK23: 177.3 | AL23: =AL14/AC23 -> 257.48928 | AM23: =AM14/AC23 -> 258.87962 | AN23: =AN14/AC23 -> 260.27691
C24: Admin Costs | D24: 20000 | AH24: =(AH23-AH21)/AH21 -> 0.10481191 | AI24: =(AI23-AI21)/AI21 -> 0.15801043 | AJ24: =(AJ23-AJ21)/AJ21 -> -0.075074119 | AK24: =(AK23-AK21)/AK21 -> -0.04694717 | AL24: =(AL23-AL21)/AL21 -> -0.20825892 | AM24: =(AM23-AM21)/AM21 -> -0.20956846 | AN24: =(AN23-AN21)/AN21 -> -0.21086617
C25: Discount to FMV for buildings under cost | D25: 0 | AA25: Discount / Premium vs. Net Asset Value (NAV)
C27: Issue Costs as a Percentage of Gross Funded Value | D27: 0 | AA27: Compounded Annual Return (Excluding Distributions) | AL27: =((AL23/100)^(1/8))-1 -> 0.12549843
C28: Issuing Agents Fee - First Secured Mortgage Debentures | D28: 0 | AA28: Distribution Yield to Buyers at Market Value | AL28: =AL14/AL23 -> 0.074 | AM28: =AM14/AM23 -> 0.074 | AN28: =AN14/AN23 -> 0.074
C29: Interest Paid to the First Secured Mortgage Debentures | D29: 0
C30: Interest earned on Cash on Hand | D30: 0.02 | AA30: Interest Coverage Ratio | AE30: - | AF30: - | AG30: - | AH30: 0 | AI30: 0 | AJ30: 0 | AK30: 0 | AL30: 0 | AM30: 0 | AN30: 0
C31: Debenture Buy Back (% of EBITDA) | D31: 0 | AA31: Debt vs. Development Cost | AE31: - | AF31: - | AG31: - | AH31: =H106 -> 0 | AI31: =I106 -> 0 | AJ31: =J106 -> 0 | AK31: =K106 -> 0 | AL31: =L106 -> 0 | AM31: =M106 -> 0 | AN31: =N106 -> 0
AA32: Debt to Asset Value | AE32: - | AF32: - | AG32: - | AH32: =AH19/AH18 -> 0 | AI32: =AI19/AI18 -> 0 | AJ32: =AJ19/AJ18 -> 0 | AK32: =AK19/AK18 -> 0 | AL32: =AL19/AL18 -> 0 | AM32: =AM19/AM18 -> 0 | AN32: =AN19/AN18 -> 0
C33: Minimum cash balance | D33: 15000
C34: Working Capital Reserve during development | D34: 0.051 | AA34: Total Expense Ratio (NAV) | AE34: =E117 -> 0.017293998 | AF34: =F117 -> 0.017547086 | AG34: =G117 -> 0.017867375 | AH34: =H117 -> 0.013437036 | AI34: =I117 -> 0.013412367 | AJ34: =J117 -> 0.0082516079 | AK34: =K117 -> 0.008224396 | AL34: =L117 -> 0.0047045686 | ... AN34: =N117 -> 0.004638855
AA35: Total Square Foot - $10 Million Gross Funded Value | AE35: - | AF35: - | AG35: - | AH35: =+F6 -> 30612.903 | AI35: =AH35 -> 30612.903 | AJ35: =+AI35+F7 -> 30612.903 | AK35: =AJ35 -> 30612.903 | AL35: =(D43+D48+D49)/E6 -> 30612.903 | AM35: =AL35 -> 30612.903 | AN35: =AM35 -> 30612.903
C37: Equity Proceeds
C38: Partner Contributions | D38: =D15-D32 -> 10000000 | AA38: Year 8 | AE38: $ | AF38: %
C39: Issuing Agents Fees | D39: =D17*D38 -> 0
C40: Issue Costs | D40: =+D27*D38 -> 0 | AA40: Revenue | AE40: =AL13 -> 20.577032 | AF40: =AE40/AE40 -> 1
C41: Net Proceeds | D41: =D38-D39-D40 -> 10000000
C42: Working Capital | D42: =D34*D38 -> 510000 | AB42: Advisory Fee | AE42: =L63/D45 -> 0.900009 | AF42: =AE42/AE40 -> 0.043738524
C43: Net Equity Funding | D43: =D41-D42 -> 9490000
AB44: Operating and Administrative Expense | AE44: =(L64+L65)/D45 -> 0.6300063 | AF44: =AE44/AE40 -> 0.030616967
C45: Number of Diluted Units | D45: =ROUND(+((D38/D16)/(1-D21)),0)-1 -> 111110 | AB45: Interest Payments | AE45: =(L69/D45)*-1 -> -0.0071898611 | AF45: =AE45/AE40 -> -0.00034941196
C47: Debt Proceeds | E47: Gross borrowing | AA47: Distributable Income
C48: Initial Financing (net of 3% cost) | D48: =+E48-E48*0.03 -> 0 | E48: 0
C49: Secondary Financing (net of 3% cost) | D49: =+E49-E49*0.03 -> 0 | E49: 0 | AB49: Repurchase Of Debentures | AE49: =(L83/D45)*-1 -> 0 | AF49: =AE49/AE40 -> 0
C50: Total (max) Debt Financing | E50: =SUM(E48:E49) -> 0 | AB50: Distributions | AE50: =(L84/D45)*-1 -> 19.054206 | AF50: =AE50/AE40 -> 0.92599392
E55: 1 | F55: 2 | G55: 3 | H55: 4 | I55: 5 | J55: 6 | K55: 7 | L55: 8 | M55: 9 | N55: 10 | O55: 11 | P55: 12 | Q55: 13 | R55: 14 | S55: 15 | T55: 16 | U55: 17 | V55: 18 | W55: 19 | X55: 20
C56: Income
C57: Net proceeds from operations | E57: =($D$43/100)*('[1]PCLP 1_250M'!E123*100) -> 0 | F57: =($D$43/100)*('[1]PCLP 1_250M'!F123*100) -> 0 | G57: =($D$43/100)*('[1]PCLP 1_250M'!G123*100) -> 0 | H57: =($D$43/100)*('[1]PCLP 1_250M'!H123*100) -> 136813.7 | I57: =($D$43/100)*('[1]PCLP 1_250M'!I123*100) -> 190709.57 | J57: =($D$43/100)*('[1]PCLP 1_250M'!J123*100) -> 270282.38 | K57: =($D$43/100)*('[1]PCLP 1_250M'!K123*100) -> 403258.44 | L57: =($D$43/100)*('[1]PCLP 1_250M'!L123*100) -> 2286314 | ... X57: =($D$43/100)*('[1]PCLP 1_250M'!X123*100) -> 2427328.9
C58: Income Continuity | D58: (Note-1) | E58: 0 | F58: 0 | G58: 0 | H58: =SUM(H57:H57) -> 136813.7 | I58: =SUM(I57:I57) -> 190709.57 | J58: =SUM(J57:J57) -> 270282.38 | K58: =SUM(K57:K57) -> 403258.44 | L58: =SUM(L57:L57) -> 2286314 | M58: =SUM(M57:M57) -> 2297745.6 | N58: =SUM(N57:N57) -> 2309234.3 | O58: =SUM(O57:O57) -> 2320780.5 | ... X58: =SUM(X57:X57) -> 2427328.9
C60: Expenses & Fees
C61: Issue Costs | E61: =$D27*$D15 -> 0 | F61: 0 | G61: 0 | H61: 0 | I61: 0 | J61: 0 | K61: 0 | L61: 0 | M61: 0 | N61: 0 | O61: 0 | P61: 0 | Q61: 0 | R61: 0 | S61: 0 | T61: 0 | U61: 0 | V61: 0 | W61: 0 | X61: 0
C62: Financing costs | E62: =D39 -> 0 | F62: 0 | G62: 0 | H62: =D28*E48 -> 0 | I62: 0 | J62: =D28*E49 -> 0 | K62: 0 | L62: 0 | M62: 0 | N62: 0 | O62: 0 | P62: 0 | Q62: 0 | R62: 0 | S62: 0 | T62: 0 | U62: 0 | V62: 0 | W62: 0 | X62: 0
C63: Advisory Fees | E63: =$D19*$D15 -> 100000 | F63: =$D19*$D15 -> 100000 | G63: =$D19*$D15 -> 100000 | H63: =$D19*$D15 -> 100000 | I63: =$D19*$D15 -> 100000 | J63: =$D19*$D15 -> 100000 | K63: =$D19*$D15 -> 100000 | L63: =$D19*$D15 -> 100000 | ... X63: =$D19*$D15 -> 100000
C64: Admin and Compliance | E64: =$D24 -> 20000 | F64: =$D24 -> 20000 | G64: =$D24 -> 20000 | H64: =$D24 -> 20000 | I64: =$D24 -> 20000 | J64: =$D24 -> 20000 | K64: =$D24 -> 20000 | L64: =$D24 -> 20000 | ... X64: =$D24 -> 20000
C65: Board of Directors | E65: =+$D23 -> 50000 | F65: =+$D23 -> 50000 | G65: =+$D23 -> 50000 | H65: =+$D23 -> 50000 | I65: =+$D23 -> 50000 | J65: =+$D23 -> 50000 | K65: =+$D23 -> 50000 | L65: =+$D23 -> 50000 | ... X65: =+$D23 -> 50000
C66: Total Expenses | E66: =SUM(E61:E65) -> 170000 | F66: =SUM(F61:F65) -> 170000 | G66: =SUM(G61:G65) -> 170000 | H66: =SUM(H61:H65) -> 170000 | I66: =SUM(I61:I65) -> 170000 | J66: =SUM(J61:J65) -> 170000 | K66: =SUM(K61:K65) -> 170000 | L66: =SUM(L61:L65) -> 170000 | ... X66: =SUM(X61:X65) -> 170000
C68: Earnings before interest, taxes and depreciation (EBITDA) | E68: =+E57-E66 -> -170000 | F68: =+F57-F66 -> -170000 | G68: =+G57-G66 -> -170000 | H68: =+H58-H66 -> -33186.303 | I68: =+I58-I66 -> 20709.565 | J68: =+J58-J66 -> 100282.38 | K68: =+K58-K66 -> 233258.44 | L68: =+L58-L66 -> 2116314 | M68: =+M58-M66 -> 2127745.6 | N68: =+N58-N66 -> 2139234.3 | O68: =+O58-O66 -> 2150780.5 | ... X68: =+X58-X66 -> 2257328.9
C69: Cost of Debenture Debt net of interest on funds on deposit | E69: =(SUM(E79)*$D$30)-((E89+E92)/2*$D$29) -> 0 | F69: =(SUM(F79)*$D$30)-((F89+F92)/2*$D$29) -> 6750.5988 | G69: =(SUM(G79)*$D$30)-((G89+G92)/2*$D$29) -> 3485.6108 | H69: =(SUM(H79)*$D$30)-((H89+H92)/2*$D$29) -> 155.32304 | I69: =(SUM(I79)*$D$30)-((I89+I92)/2*$D$29) -> 89.261076 | J69: =(SUM(J79)*$D$30)-((J89+J92)/2*$D$29) -> 130.85873 | K69: =(SUM(K79)*$D$30)-((K89+K92)/2*$D$29) -> 331.68521 | L69: =(SUM(L79)*$D$30)-(L89*$D$29) -> 798.86547 | M69: =(SUM(M79)*$D$30)-(M89*$D$29) -> 798.86547 | N69: =(SUM(N79)*$D$30)-(N89*$D$29) -> 798.86547 | O69: =(SUM(O79)*$D$30)-(O89*$D$29) -> 798.86547 | P69: =(SUM(P79)*$D$30)-(P89*$D$29) -> 798.88547 | Q69: =(SUM(Q79)*$D$30)-(Q89*$D$29) -> 798.92547 | R69: =(SUM(R79)*$D$30)-(R89*$D$29) -> 798.98547 | S69: =(SUM(S79)*$D$30)-(S89*$D$29) -> 799.06547 | ... X69: =(SUM(X79)*$D$30)-(X89*$D$29) -> 799.76547
C70: Percentage Interest Payable - net of interest income | H70: =(H69/H92)*-1 -> #DIV/0! | I70: =(I69/I92)*-1 -> #DIV/0! | J70: =(J69/J92)*-1 -> #DIV/0! | K70: =(K69/K92)*-1 -> #DIV/0! | L70: =(L69/L92)*-1 -> #DIV/0! | M70: =(M69/M92)*-1 -> #DIV/0! | N70: =(N69/N92)*-1 -> #DIV/0! | O70: =(O69/O92)*-1 -> #DIV/0! | ... X70: =(X69/X92)*-1 -> #DIV/0!
C72: Funding from operations | E72: =SUM(E68:E69) -> -170000 | F72: =SUM(F68:F69) -> -163249.4 | G72: =SUM(G68:G69) -> -166514.39 | H72: =SUM(H68:H69) -> -33030.98 | I72: =SUM(I68:I69) -> 20798.827 | J72: =SUM(J68:J69) -> 100413.24 | K72: =SUM(K68:K69) -> 233590.13 | L72: =SUM(L68:L69) -> 2117112.9 | ... X72: =SUM(X68:X69) -> 2258128.6
C74: Interest Coverage Ratio | E74: n/a | F74: n/a | G74: n/a | H74: =H68/H69*-1 -> 213.65989 | I74: =I68/I69*-1 -> -232.01116 | J74: =J68/J69*-1 -> -766.34079 | K74: =K68/K69*-1 -> -703.25247 | L74: =L68/L69*-1 -> -2649.1494 | M74: =M68/M69*-1 -> -2663.4592 | N74: =N68/N69*-1 -> -2677.8405 | O74: =O68/O69*-1 -> -2692.2937 | ... X74: =X68/X69*-1 -> -2822.4885
C75: Debt Service Ratio | E75: n/a | F75: n/a | G75: n/a | H75: =+H68/(-H69-H91) -> 213.65989 | I75: =+I68/(-I69-I91) -> -232.01116 | J75: =+J68/(-J69-J91) -> -766.34079 | K75: =+K68/(-K69-K91) -> -703.25247 | L75: =+L68/(-L69-L91) -> -2649.1494 | M75: =+M68/(-M69-M91) -> -2663.4592 | N75: =+N68/(-N69-N91) -> -2677.8405 | O75: =+O68/(-O69-O91) -> -2692.2937 | ... X75: =+X68/(-X69-X91) -> -2822.4885
C76: Proceeds as a % of EBITDA | E76: n/a | F76: n/a | G76: n/a | H76: =H68/H58 -> -0.24256565 | I76: =I68/I58 -> 0.10859217 | J76: =J68/J58 -> 0.37102819 | K76: =K68/K58 -> 0.57843412 | L76: =L68/L58 -> 0.92564451 | M76: =M68/M58 -> 0.92601444 | N76: =N68/N58 -> 0.92638252 | O76: =O68/O58 -> 0.92674878 | ... X76: =X68/X58 -> 0.92996417
C78: Cash Flow Continuity
C79: Opening Cash | E79: 0 | F79: =E86 -> 337529.94 | G79: =F86 -> 174280.54 | H79: =G86 -> 7766.1518 | I79: =H86 -> 4463.0538 | J79: =I86 -> 6542.9364 | K79: =J86 -> 16584.26 | L79: =K86 -> 39943.273 | M79: =L86 -> 39943.273 | ... X79: =W86 -> 39988.273
C80: New Equity Financing | E80: =$D$38 -> 10000000 | F80: 0 | G80: 0 | H80: 0 | I80: 0 | J80: 0 | K80: 0 | L80: 0 | M80: 0 | N80: 0 | O80: 1 | P80: 2 | Q80: 3 | R80: 4 | S80: 5 | T80: 6 | U80: 7 | V80: 8 | W80: 9 | X80: 10
C81: New Debt Financing (gross) | E81: =E90 -> 0 | F81: =F90 -> 0 | G81: =G90 -> 0 | H81: =H90 -> 0 | I81: =I90 -> 0 | J81: =J90 -> 0 | K81: =K90 -> 0 | L81: =L90 -> 0 | ... X81: =X90 -> 0
C82: Capital Asset Additions | E82: =-E100 -> -9492470.1 | F82: =-F100+F96 -> 0 | G82: =-G100+G96 -> 0 | H82: =-H100+H96 -> 0 | I82: =-I100+I96 -> 0 | J82: =-J100+J96 -> 0 | K82: =-K100+K96 -> 0 | L82: =-L100+L96 -> 0 | M82: =-M100+M96 -> 0 | ... X82: =-X100+X96 -> 0
C83: Debt Repayment | E83: =E91 -> 0 | F83: =F91 -> 0 | G83: =G91 -> 0 | H83: =H91 -> 0 | I83: =I91 -> 0 | J83: =J91 -> 0 | K83: =K91 -> 0 | L83: =L91 -> 0 | ... X83: =X91 -> 0
C84: Distributions | E84: =-E120 -> 0 | F84: =-F120 -> 0 | G84: =-G120 -> 0 | H84: =-H120 -> 29727.882 | I84: =-I120 -> -18718.944 | J84: =-J120 -> -90371.916 | K84: =-K120 -> -210231.12 | L84: =-L120 -> -2117112.9 | ... X84: =-X120 -> -2258128.6
C85: =+C72 -> Funding from operations | E85: =E72 -> -170000 | F85: =F72 -> -163249.4 | G85: =G72 -> -166514.39 | H85: =H72 -> -33030.98 | I85: =I72 -> 20798.827 | J85: =J72 -> 100413.24 | K85: =K72 -> 233590.13 | L85: =L72 -> 2117112.9 | ... X85: =X72 -> 2258128.6
C86: Ending Cash | E86: =SUM(E79:E85) -> 337529.94 | F86: =SUM(F79:F85) -> 174280.54 | G86: =SUM(G79:G85) -> 7766.1518 | H86: =SUM(H79:H85) -> 4463.0538 | I86: =SUM(I79:I85) -> 6542.9364 | J86: =SUM(J79:J85) -> 16584.26 | K86: =SUM(K79:K85) -> 39943.273 | L86: =SUM(L79:L85) -> 39943.273 | ... X86: =SUM(X79:X85) -> 39998.273
C88: Debenture Continuity
C89: Opening Debt | E89: 0 | F89: =E92 -> 0 | G89: =F92 -> 0 | H89: =G92 -> 0 | I89: =H92 -> 0 | J89: =I92 -> 0 | K89: =J92 -> 0 | L89: =K92 -> 0 | M89: =L92 -> 0 | ... X89: =W92 -> 0
C90: Additions | E90: 0 | F90: 0 | G90: 0 | H90: =+E48/2 -> 0 | I90: =+E48/2 -> 0 | J90: =+E49/2 -> 0 | K90: 0 | L90: 0 | M90: =SUM(M97:M99) -> 0 | N90: =SUM(N97:N99) -> 0 | O90: =SUM(O97:O99) -> 0 | P90: =SUM(P97:P99) -> 0 | Q90: =SUM(Q97:Q99) -> 0 | R90: =SUM(R97:R99) -> 0 | S90: =SUM(S97:S99) -> 0 | T90: =SUM(T97:T99) -> 0 | ... X90: =SUM(X97:X99) -> 0
C91: Payments | E91: 0 | F91: 0 | G91: 0 | H91: 0 | L91: =-L72*$D31 -> 0 | M91: =-M72*$D31 -> 0 | N91: =-N72*$D31 -> 0 | O91: =-O72*$D31 -> 0 | P91: =-P72*$D31 -> 0 | Q91: =-Q72*$D31 -> 0 | R91: =-R72*$D31 -> 0 | S91: =-S72*$D31 -> 0 | ... X91: =-X72*$D31 -> 0
C92: Ending Debt | E92: =SUM(E89:E91) -> 0 | F92: =SUM(F89:F91) -> 0 | G92: =SUM(G89:G91) -> 0 | H92: =SUM(H89:H91) -> 0 | I92: =SUM(I89:I91) -> 0 | J92: =SUM(J89:J91) -> 0 | K92: =SUM(K89:K91) -> 0 | L92: =SUM(L89:L91) -> 0 | ... X92: =SUM(X89:X91) -> 0
C95: Asset Continuity
C96: Opening Assets | E96: =($D$43/100)*'[1]PCLP 1_250M'!E115 -> 9492470.1 | F96: =($D$43/100)*'[1]PCLP 1_250M'!F115 -> 9513938 | G96: =($D$43/100)*'[1]PCLP 1_250M'!G115 -> 9506782.3 | H96: =($D$43/100)*'[1]PCLP 1_250M'!H115 -> 12647137 | I96: =($D$43/100)*'[1]PCLP 1_250M'!I115 -> 12668327 | J96: =($D$43/100)*'[1]PCLP 1_250M'!J115 -> 20585461 | K96: =($D$43/100)*'[1]PCLP 1_250M'!K115 -> 20630268 | L96: =($D$43/100)*'[1]PCLP 1_250M'!L115 -> 36095145 | ... X96: =($D$43/100)*'[1]PCLP 1_250M'!X115 -> 45366994
C97: =+C6 -> Phase 1 - initial funding for capital assets | E97: 0 | F97: 0 | G97: 0 | H97: 0 | I97: 0 | J97: 0 | K97: 0 | L97: 0 | M97: 0 | N97: 0 | O97: 0 | P97: 0 | Q97: 0 | R97: 0 | S97: 0 | T97: 0 | U97: 0 | V97: 0 | W97: 0 | X97: 0
C98: =+C7 -> Phase 2 - first financing | E98: 0 | F98: 0 | G98: 0 | H98: =($F$7*$E$7)/$D7 -> 0 | I98: =($F$7*$E$7)/$D7 -> 0 | J98: 0 | K98: 0 | L98: 0 | M98: 0 | N98: 0 | O98: 0 | P98: 0 | Q98: 0 | R98: 0 | S98: 0 | T98: 0 | U98: 0 | V98: 0 | W98: 0 | X98: 0
C99: =+C8 -> Phase 3 - second financing | E99: 0 | F99: 0 | G99: 0 | H99: 0 | I99: 0 | J99: =($F8*$E8)/$D8 -> 0 | K99: =($F8*$E8)/$D8 -> 0 | L99: 0 | M99: 0 | N99: 0 | O99: 0 | P99: 0 | Q99: 0 | R99: 0 | S99: 0 | T99: 0 | U99: 0 | V99: 0 | W99: 0 | X99: 0
C100: Total Capital Assets | E100: =SUM(E96:E99) -> 9492470.1 | F100: =SUM(F96:F99) -> 9513938 | G100: =SUM(G96:G99) -> 9506782.3 | H100: =SUM(H96:H99) -> 12647137 | I100: =SUM(I96:I99) -> 12668327 | J100: =SUM(J96:J99) -> 20585461 | K100: =SUM(K96:K99) -> 20630268 | L100: =SUM(L96:L99) -> 36095145 | ... X100: =SUM(X96:X99) -> 45366994
C102: Total Capital Assets Generating Rent | E102: 0 | F102: 0 | G102: 0 | H102: 0 | I102: 0 | J102: 0 | K102: 0 | L102: 0 | M102: 0 | N102: 0 | O102: 0 | P102: 0 | Q102: 0 | R102: 0 | S102: 0 | T102: 0 | U102: 0 | V102: 0 | W102: 0 | X102: 0
C104: Buildings under construction | E104: 0 | F104: 0 | G104: 0 | H104: 0 | I104: 0 | J104: 0 | K104: 0 | L104: 0 | M104: 0 | N104: 0 | O104: 0 | P104: 0 | Q104: 0 | R104: 0 | S104: 0 | T104: 0 | U104: 0 | V104: 0 | W104: 0 | X104: 0
C105: FMV of building under construction | E105: =E104*(1-$D$25) -> 0 | F105: =F104*(1-$D$25) -> 0 | G105: =G104*(1-$D$25) -> 0 | H105: =H104*(1-$D$25) -> 0 | I105: =I104*(1-$D$25) -> 0 | J105: =J104*(1-$D$25) -> 0 | K105: =K104*(1-$D$25) -> 0 | L105: =L104*(1-$D$25) -> 0 | ... X105: =X104*(1-$D$25) -> 0
C106: Debt to development cost | E106: =E92/E100 -> 0 | F106: =F92/F100 -> 0 | G106: =G92/G100 -> 0 | H106: =H92/H100 -> 0 | I106: =I92/I100 -> 0 | J106: =J92/J100 -> 0 | K106: =K92/K100 -> 0 | L106: =L92/L100 -> 0 | ... X106: =X92/X100 -> 0
C108: Asset Valuation
C109: Cap Rate - Public Non Listed | E109: =E100+E86 -> 9830000 | F109: =F100+F86 -> 9688218.6 | G109: =G100+G86 -> 9514548.4 | H109: =H100+H86 -> 12651600 | I109: =I100+I86 -> 12674869 | J109: =J100+J86 -> 20602045 | K109: =K100+K86 -> 20670211 | L109: =L100+L86 -> 36135088 | ... X109: =X100+X86 -> 45406992
C110: Asset Valuation (per diluted Unit) | E110: =+E109/$D$45 -> 88.470885 | F110: =+F109/$D$45 -> 87.194839 | G110: =+G109/$D$45 -> 85.631792 | H110: =+H109/$D$45 -> 113.86554 | I110: =+I109/$D$45 -> 114.07497 | J110: =+J109/$D$45 -> 185.42026 | K110: =+K109/$D$45 -> 186.03376 | L110: =L109/$D$45 -> 325.21904 | M110: =M109/$D$45 -> 327.51681 | N110: =N109/$D$45 -> 329.82607 | O110: =O109/$D$45 -> 387.25009 | P110: =P109/$D$45 -> 389.58252 | Q110: =Q109/$D$45 -> 391.92661 | R110: =R109/$D$45 -> 394.28244 | S110: =S109/$D$45 -> 396.65005 | ... X110: =X109/$D$45 -> 408.66701
C112: Net Asset Valuations
C114: Cap Rate - Public Non Listed | E114: =E109-E92 -> 9830000 | F114: =F109-F92 -> 9688218.6 | G114: =G109-G92 -> 9514548.4 | H114: =H109-H92 -> 12651600 | I114: =I109-I92 -> 12674869 | J114: =J109-J92 -> 20602045 | K114: =K109-K92 -> 20670211 | L114: =L109-L92 -> 36135088 | ... X114: =X109-X92 -> 45406992
C115: Asset Valuation (per diluted Unit) | E115: =E114/$D45 -> 88.470885 | F115: =F114/$D45 -> 87.194839 | G115: =G114/$D45 -> 85.631792 | H115: =H114/$D45 -> 113.86554 | I115: =I114/$D45 -> 114.07497 | J115: =J114/$D45 -> 185.42026 | K115: =K114/$D45 -> 186.03376 | L115: =L114/$D45 -> 325.21904 | ... X115: =X114/$D45 -> 408.66701
C116: Distribution Yield | E116: =E122/E115 -> 0 | F116: =F122/F115 -> 0 | G116: =G122/G115 -> 0 | H116: =H122/H115 -> -0.0023497331 | I116: =I122/I115 -> 0.001476855 | J116: =J122/J115 -> 0.0043865507 | K116: =K122/K115 -> 0.010170729 | L116: =L122/L115 -> 0.05858884 | ... X116: =X122/X115 -> 0.049730857
C117: Total Expense Ratio vs NAV ( excluding financing costs ) | E117: =SUM(E63:E65)/E114 -> 0.017293998 | F117: =SUM(F63:F65)/F114 -> 0.017547086 | G117: =SUM(G63:G65)/G114 -> 0.017867375 | H117: =SUM(H63:H65)/H114 -> 0.013437036 | I117: =SUM(I63:I65)/I114 -> 0.013412367 | J117: =SUM(J63:J65)/J114 -> 0.0082516079 | K117: =SUM(K63:K65)/K114 -> 0.008224396 | L117: =SUM(L63:L65)/L114 -> 0.0047045686 | ... X117: =SUM(X63:X65)/X114 -> 0.0037439168
C119: Distribution Analysis
C120: Distribution to Limited Partners | E120: 0 | F120: 0 | G120: 0 | H120: =+H72*0.9+H91 -> -29727.882 | I120: =+I72*0.9+I91 -> 18718.944 | J120: =+J72*0.9+J91 -> 90371.916 | K120: =+K72*0.9+K91 -> 210231.12 | L120: =+L72+L91+L90 -> 2117112.9 | M120: =+M72+M91 -> 2128544.4 | N120: =+N72+N91 -> 2140033.2 | O120: =+O72+O91 -> 2151579.3 | P120: =+P72+P91 -> 2163183.3 | Q120: =+Q72+Q91 -> 2174845.2 | R120: =+R72+R91 -> 2186565.5 | S120: =+S72+S91 -> 2198344.4 | T120: =+T72+T91 -> 2210182.3 | ... X120: =+X72+X91 -> 2258128.6
C122: Distribution per Diluted Unit | E122: 0 | F122: 0 | G122: 0 | H122: =H120/$D45 -> -0.26755361 | I122: =I120/$D45 -> 0.16847218 | J122: =J120/$D45 -> 0.81335538 | K122: =K120/$D45 -> 1.892099 | L122: =L120/$D45 -> 19.054206 | M122: =M120/$D45 -> 19.157092 | N122: =N120/$D45 -> 19.260491 | O122: =O120/$D45 -> 19.364408 | ... X122: =X120/$D45 -> 20.323361
C123: Distribution Yield (on original $100 investment) | E123: =E122/$D16 -> 0 | F123: =F122/$D16 -> 0 | G123: =G122/$D16 -> 0 | H123: =H122/$D16 -> -0.0026755361 | I123: =I122/$D16 -> 0.0016847218 | J123: =J122/$D16 -> 0.0081335538 | K123: =K122/$D16 -> 0.01892099 | L123: =L122/$D16 -> 0.19054206 | ... X123: =X122/$D16 -> 0.20323361
C125: Distribution year over year growth | E125: 0 | F125: 0 | G125: 0 | H125: 0 | I125: =(I122-H122)/H122 -> -1.6296763 | J125: =(J122-I122)/I122 -> 3.827832 | K125: =(K122-J122)/J122 -> 1.3262881 | L125: =(L122-K122)/K122 -> 9.0704069 | M125: =(M122-L122)/L122 -> 0.0053996035 | N125: =(N122-M122)/M122 -> 0.0053974574 | O125: =(O122-N122)/N122 -> 0.0053953236 | P125: =(P122-O122)/O122 -> 0.0053932115 | ... S125: =(S122-R122)/R122 -> 0.0053869471 | T125: =+(T122-S122)/S122 -> 0.0053848827 | U125: =+(U122-T122)/T122 -> 0.0053828301 | V125: =+(V122-U122)/U122 -> 0.0053807891 | W125: =+(W122-V122)/V122 -> 0.0053787598 | X125: =+(X122-W122)/W122 -> 0.005376742
C127: Earnings Before Taxes, Depreciation and Interest on the Debt | E127: =E68/$D$45 -> -1.5300153 | F127: =F68/$D$45 -> -1.5300153 | G127: =G68/$D$45 -> -1.5300153 | H127: =H68/$D$45 -> -0.29867971 | I127: =I68/$D$45 -> 0.18638795 | J127: =J68/$D$45 -> 0.90255046 | K127: =K68/$D$45 -> 2.099347 | L127: =L68/$D$45 -> 19.047017 | ... X127: =X68/$D$45 -> 20.316163
...

Sheet SPV_Compensations_15 percent
C1: Cash Flow and Valuation
C2: Woodfine Professional Centres Limited Partnership
C3: January 6, 2026
D5: Build Time | E5: Gross Cost per sq. ft. | F5: Portfolio additions in sf. | G5: Capital investment
C6: Phase 1 - initial funding for capital assets | D6: 1 | E6: 310 | F6: =$D$43/$E6 -> 30612.903 | G6: =+F6*E6 -> 9490000 | AA6: SPV Arrangements - Asset Manager Dilution
C7: Phase 2 - first financing | D7: 2 | E7: =+E6 -> 310 | F7: =$D$48/$E7 -> 0 | G7: =+F7*E7 -> 0 | AA7: Unit-based Compensation | AC7: =D21 -> 0.15 | AI7: Management Fee (1% GFV) | AL7: =SUM(E63:L63) -> 800000
C8: Phase 3 - second financing | D8: 2 | E8: =+E7 -> 310 | F8: =$D$49/$E8 -> 0 | G8: =+F8*E8 -> 0 | AA8: =C23 -> Board of Directors Expense | AC8: =D23 -> 50000 | AI8: Unit-based Compenstion (10% Market Value) | AL8: =AL23*(D45-100000) -> 4291226.2
F9: =SUM(F6:F8) -> 30612.903 | G9: =SUM(G6:G8) -> 9490000 | AA9: =C24 -> Admin Costs | AC9: =D24 -> 20000 | AI9: Distributions | AL9: =SUM(E120:L120)*AC7 -> 361006.05
C10: Development Yield | D10: 0.105 | AA10: Working Capital Reserve | AC10: =D34 -> 0.051
AA11: Minimum Cash Position | AC11: =H86 -> 4463.0538
C12: Cap Rate - Public Non Listed | D12: 0.0625 | AE12: Y1 | AF12: Y2 | AG12: Y3 | AH12: Y4 | AI12: Y5 | AJ12: Y6 | AK12: Y7 | AL12: Y8 | AM12: Y9 | AN12: Y10
AA13: Revenue | AE13: - | AF13: - | AG13: - | AH13: =H57/$D45 -> 1.1629269 | AI13: =I57/$D45 -> 1.6210459 | AJ13: =J57/$D45 -> 2.2974209 | AK13: =K57/$D45 -> 3.4277276 | AL13: =L57/$D45 -> 19.433844 | AM13: =M57/$D45 -> 19.531013 | AN13: =N57/$D45 -> 19.628668
AA14: Distributions | AE14: - | AF14: - | AG14: - | AH14: =H122 -> -0.25268927 | AI14: =I122 -> 0.15911245 | AJ14: =J122 -> 0.7681682 | AK14: =K122 -> 1.7869806 | AL14: =L122 -> 17.995621 | AM14: =M122 -> 18.092791 | AN14: =N122 -> 18.190446
C15: Total Equity Financing - 1 year | D15: 10000000
C16: Cost per Unit | D16: 100 | AA16: Distribution Yield on Initial Capital | AE16: - | AF16: - | AG16: - | AH16: =AH14/100 -> -0.0025268927 | AI16: =AI14/100 -> 0.0015911245 | AJ16: =AJ14/100 -> 0.007681682 | AK16: =AK14/100 -> 0.017869806 | AL16: =AL14/100 -> 0.17995621 | AM16: =AM14/100 -> 0.18092791 | AN16: =AN14/100 -> 0.18190446
C17: Issuing Agents Fee | D17: 0
AA18: Asset Value | AE18: =E110 -> 83.555752 | AF18: =F110 -> 82.350599 | AG18: =G110 -> 80.874389 | AH18: =H110 -> 107.53956 | AI18: =I110 -> 107.73736 | AJ18: =J110 -> 175.11896 | AK18: =K110 -> 175.69837 | AL18: =L110 -> 307.15101 | ... AN18: =N110 -> 311.50209
C19: Advisory Fee as percentage of Gross Funded Value | D19: 0.01 | AA19: Total Debt | AE19: =E92/$D45 -> 0 | AF19: =F92/$D45 -> 0 | AG19: =G92/$D45 -> 0 | AH19: =H92/$D45 -> 0 | AI19: =I92/$D45 -> 0 | AJ19: =J92/$D45 -> 0 | AK19: =K92/$D45 -> 0 | AL19: =L92/$D45 -> 0 | ... AN19: =N92/$D45 -> 0
C21: Benetti Holdings Dilution | D21: 0.15 | AA21: Net Asset Value (NAV) | AE21: =E115 -> 83.555752 | AF21: =F115 -> 82.350599 | AG21: =G115 -> 80.874389 | AH21: =H115 -> 107.53956 | AI21: =I115 -> 107.73736 | AJ21: =J115 -> 175.11896 | AK21: =K115 -> 175.69837 | AL21: =L115 -> 307.15101 | ... AN21: =N115 -> 311.50209
C23: Board of Directors Expense | D23: 50000 | AA23: Market Value | AC23: 0.074 | AE23: 100 | AF23: 100 | AG23: 100 | AH23: 125.8 | AI23: 132.1 | AJ23: 171.5 | AK23: 177.3 | AL23: =AL14/AC23 -> 243.18407 | AM23: =AM14/AC23 -> 244.49717 | AN23: =AN14/AC23 -> 245.81683
C24: Admin Costs | D24: 20000 | AH24: =(AH23-AH21)/AH21 -> 0.16980202 | AI24: =(AI23-AI21)/AI21 -> 0.22612991 | AJ24: =(AJ23-AJ21)/AJ21 -> -0.020665735 | AK24: =(AK23-AK21)/AK21 -> 0.0091157699 | AL24: =(AL23-AL21)/AL21 -> -0.20825892 | AM24: =(AM23-AM21)/AM21 -> -0.20956846 | AN24: =(AN23-AN21)/AN21 -> -0.21086617
C25: Discount to FMV for buildings under cost | D25: 0 | AA25: Discount / Premium vs. Net Asset Value (NAV)
C27: Issue Costs as a Percentage of Gross Funded Value | D27: 0 | AA27: Compounded Annual Return (Excluding Distributions) | AL27: =((AL23/100)^(1/8))-1 -> 0.11748549
C28: Issuing Agents Fee - First Secured Mortgage Debentures | D28: 0 | AA28: Distribution Yield to Buyers at Market Value | AL28: =AL14/AL23 -> 0.074 | AM28: =AM14/AM23 -> 0.074 | AN28: =AN14/AN23 -> 0.074
C29: Interest Paid to the First Secured Mortgage Debentures | D29: 0
C30: Interest earned on Cash on Hand | D30: 0.02 | AA30: Interest Coverage Ratio | AE30: - | AF30: - | AG30: - | AH30: 0 | AI30: 0 | AJ30: 0 | AK30: 0 | AL30: 0 | AM30: 0 | AN30: 0
C31: Debenture Buy Back (% of EBITDA) | D31: 0 | AA31: Debt vs. Development Cost | AE31: - | AF31: - | AG31: - | AH31: =H106 -> 0 | AI31: =I106 -> 0 | AJ31: =J106 -> 0 | AK31: =K106 -> 0 | AL31: =L106 -> 0 | AM31: =M106 -> 0 | AN31: =N106 -> 0
AA32: Debt to Asset Value | AE32: - | AF32: - | AG32: - | AH32: =AH19/AH18 -> 0 | AI32: =AI19/AI18 -> 0 | AJ32: =AJ19/AJ18 -> 0 | AK32: =AK19/AK18 -> 0 | AL32: =AL19/AL18 -> 0 | AM32: =AM19/AM18 -> 0 | AN32: =AN19/AN18 -> 0
C33: Minimum cash balance | D33: 15000
C34: Working Capital Reserve during development | D34: 0.051 | AA34: Total Expense Ratio (NAV) | AE34: =E117 -> 0.017293998 | AF34: =F117 -> 0.017547086 | AG34: =G117 -> 0.017867375 | AH34: =H117 -> 0.013437036 | AI34: =I117 -> 0.013412367 | AJ34: =J117 -> 0.0082516079 | AK34: =K117 -> 0.008224396 | AL34: =L117 -> 0.0047045686 | ... AN34: =N117 -> 0.004638855
AA35: Total Square Foot - $10 Million Gross Funded Value | AE35: - | AF35: - | AG35: - | AH35: =+F6 -> 30612.903 | AI35: =AH35 -> 30612.903 | AJ35: =+AI35+F7 -> 30612.903 | AK35: =AJ35 -> 30612.903 | AL35: =(D43+D48+D49)/E6 -> 30612.903 | AM35: =AL35 -> 30612.903 | AN35: =AM35 -> 30612.903
C37: Equity Proceeds
C38: Partner Contributions | D38: =D15-D32 -> 10000000 | AA38: Year 8 | AE38: $ | AF38: %
C39: Issuing Agents Fees | D39: =D17*D38 -> 0
C40: Issue Costs | D40: =+D27*D38 -> 0 | AA40: Revenue | AE40: =AL13 -> 19.433844 | AF40: =AE40/AE40 -> 1
C41: Net Proceeds | D41: =D38-D39-D40 -> 10000000
C42: Working Capital | D42: =D34*D38 -> 510000 | AB42: Advisory Fee | AE42: =L63/D45 -> 0.85000765 | AF42: =AE42/AE40 -> 0.043738524
C43: Net Equity Funding | D43: =D41-D42 -> 9490000
AB44: Operating and Administrative Expense | AE44: =(L64+L65)/D45 -> 0.59500536 | AF44: =AE44/AE40 -> 0.030616967
C45: Number of Diluted Units | D45: =ROUND(+((D38/D16)/(1-D21)),0)-1 -> 117646 | AB45: Interest Payments | AE45: =(L69/D45)*-1 -> -0.0067904176 | AF45: =AE45/AE40 -> -0.00034941196
C47: Debt Proceeds | E47: Gross borrowing | AA47: Distributable Income
C48: Initial Financing (net of 3% cost) | D48: =+E48-E48*0.03 -> 0 | E48: 0
C49: Secondary Financing (net of 3% cost) | D49: =+E49-E49*0.03 -> 0 | E49: 0 | AB49: Repurchase Of Debentures | AE49: =(L83/D45)*-1 -> 0 | AF49: =AE49/AE40 -> 0
C50: Total (max) Debt Financing | E50: =SUM(E48:E49) -> 0 | AB50: Distributions | AE50: =(L84/D45)*-1 -> 17.995621 | AF50: =AE50/AE40 -> 0.92599392
E55: 1 | F55: 2 | G55: 3 | H55: 4 | I55: 5 | J55: 6 | K55: 7 | L55: 8 | M55: 9 | N55: 10 | O55: 11 | P55: 12 | Q55: 13 | R55: 14 | S55: 15 | T55: 16 | U55: 17 | V55: 18 | W55: 19 | X55: 20
C56: Income
C57: Net proceeds from operations | E57: =($D$43/100)*('[1]PCLP 1_250M'!E123*100) -> 0 | F57: =($D$43/100)*('[1]PCLP 1_250M'!F123*100) -> 0 | G57: =($D$43/100)*('[1]PCLP 1_250M'!G123*100) -> 0 | H57: =($D$43/100)*('[1]PCLP 1_250M'!H123*100) -> 136813.7 | I57: =($D$43/100)*('[1]PCLP 1_250M'!I123*100) -> 190709.57 | J57: =($D$43/100)*('[1]PCLP 1_250M'!J123*100) -> 270282.38 | K57: =($D$43/100)*('[1]PCLP 1_250M'!K123*100) -> 403258.44 | L57: =($D$43/100)*('[1]PCLP 1_250M'!L123*100) -> 2286314 | ... X57: =($D$43/100)*('[1]PCLP 1_250M'!X123*100) -> 2427328.9
C58: Income Continuity | D58: (Note-1) | E58: 0 | F58: 0 | G58: 0 | H58: =SUM(H57:H57) -> 136813.7 | I58: =SUM(I57:I57) -> 190709.57 | J58: =SUM(J57:J57) -> 270282.38 | K58: =SUM(K57:K57) -> 403258.44 | L58: =SUM(L57:L57) -> 2286314 | M58: =SUM(M57:M57) -> 2297745.6 | N58: =SUM(N57:N57) -> 2309234.3 | O58: =SUM(O57:O57) -> 2320780.5 | ... X58: =SUM(X57:X57) -> 2427328.9
C60: Expenses & Fees
C61: Issue Costs | E61: =$D27*$D15 -> 0 | F61: 0 | G61: 0 | H61: 0 | I61: 0 | J61: 0 | K61: 0 | L61: 0 | M61: 0 | N61: 0 | O61: 0 | P61: 0 | Q61: 0 | R61: 0 | S61: 0 | T61: 0 | U61: 0 | V61: 0 | W61: 0 | X61: 0
C62: Financing costs | E62: =D39 -> 0 | F62: 0 | G62: 0 | H62: =D28*E48 -> 0 | I62: 0 | J62: =D28*E49 -> 0 | K62: 0 | L62: 0 | M62: 0 | N62: 0 | O62: 0 | P62: 0 | Q62: 0 | R62: 0 | S62: 0 | T62: 0 | U62: 0 | V62: 0 | W62: 0 | X62: 0
C63: Advisory Fees | E63: =$D19*$D15 -> 100000 | F63: =$D19*$D15 -> 100000 | G63: =$D19*$D15 -> 100000 | H63: =$D19*$D15 -> 100000 | I63: =$D19*$D15 -> 100000 | J63: =$D19*$D15 -> 100000 | K63: =$D19*$D15 -> 100000 | L63: =$D19*$D15 -> 100000 | ... X63: =$D19*$D15 -> 100000
C64: Admin and Compliance | E64: =$D24 -> 20000 | F64: =$D24 -> 20000 | G64: =$D24 -> 20000 | H64: =$D24 -> 20000 | I64: =$D24 -> 20000 | J64: =$D24 -> 20000 | K64: =$D24 -> 20000 | L64: =$D24 -> 20000 | ... X64: =$D24 -> 20000
C65: Board of Directors | E65: =+$D23 -> 50000 | F65: =+$D23 -> 50000 | G65: =+$D23 -> 50000 | H65: =+$D23 -> 50000 | I65: =+$D23 -> 50000 | J65: =+$D23 -> 50000 | K65: =+$D23 -> 50000 | L65: =+$D23 -> 50000 | ... X65: =+$D23 -> 50000
C66: Total Expenses | E66: =SUM(E61:E65) -> 170000 | F66: =SUM(F61:F65) -> 170000 | G66: =SUM(G61:G65) -> 170000 | H66: =SUM(H61:H65) -> 170000 | I66: =SUM(I61:I65) -> 170000 | J66: =SUM(J61:J65) -> 170000 | K66: =SUM(K61:K65) -> 170000 | L66: =SUM(L61:L65) -> 170000 | ... X66: =SUM(X61:X65) -> 170000
C68: Earnings before interest, taxes and depreciation (EBITDA) | E68: =+E57-E66 -> -170000 | F68: =+F57-F66 -> -170000 | G68: =+G57-G66 -> -170000 | H68: =+H58-H66 -> -33186.303 | I68: =+I58-I66 -> 20709.565 | J68: =+J58-J66 -> 100282.38 | K68: =+K58-K66 -> 233258.44 | L68: =+L58-L66 -> 2116314 | M68: =+M58-M66 -> 2127745.6 | N68: =+N58-N66 -> 2139234.3 | O68: =+O58-O66 -> 2150780.5 | ... X68: =+X58-X66 -> 2257328.9
C69: Cost of Debenture Debt net of interest on funds on deposit | E69: =(SUM(E79)*$D$30)-((E89+E92)/2*$D$29) -> 0 | F69: =(SUM(F79)*$D$30)-((F89+F92)/2*$D$29) -> 6750.5988 | G69: =(SUM(G79)*$D$30)-((G89+G92)/2*$D$29) -> 3485.6108 | H69: =(SUM(H79)*$D$30)-((H89+H92)/2*$D$29) -> 155.32304 | I69: =(SUM(I79)*$D$30)-((I89+I92)/2*$D$29) -> 89.261076 | J69: =(SUM(J79)*$D$30)-((J89+J92)/2*$D$29) -> 130.85873 | K69: =(SUM(K79)*$D$30)-((K89+K92)/2*$D$29) -> 331.68521 | L69: =(SUM(L79)*$D$30)-(L89*$D$29) -> 798.86547 | M69: =(SUM(M79)*$D$30)-(M89*$D$29) -> 798.86547 | N69: =(SUM(N79)*$D$30)-(N89*$D$29) -> 798.86547 | O69: =(SUM(O79)*$D$30)-(O89*$D$29) -> 798.86547 | P69: =(SUM(P79)*$D$30)-(P89*$D$29) -> 798.88547 | Q69: =(SUM(Q79)*$D$30)-(Q89*$D$29) -> 798.92547 | R69: =(SUM(R79)*$D$30)-(R89*$D$29) -> 798.98547 | S69: =(SUM(S79)*$D$30)-(S89*$D$29) -> 799.06547 | ... X69: =(SUM(X79)*$D$30)-(X89*$D$29) -> 799.76547
C70: Percentage Interest Payable - net of interest income | H70: =(H69/H92)*-1 -> #DIV/0! | I70: =(I69/I92)*-1 -> #DIV/0! | J70: =(J69/J92)*-1 -> #DIV/0! | K70: =(K69/K92)*-1 -> #DIV/0! | L70: =(L69/L92)*-1 -> #DIV/0! | M70: =(M69/M92)*-1 -> #DIV/0! | N70: =(N69/N92)*-1 -> #DIV/0! | O70: =(O69/O92)*-1 -> #DIV/0! | ... X70: =(X69/X92)*-1 -> #DIV/0!
C72: Funding from operations | E72: =SUM(E68:E69) -> -170000 | F72: =SUM(F68:F69) -> -163249.4 | G72: =SUM(G68:G69) -> -166514.39 | H72: =SUM(H68:H69) -> -33030.98 | I72: =SUM(I68:I69) -> 20798.827 | J72: =SUM(J68:J69) -> 100413.24 | K72: =SUM(K68:K69) -> 233590.13 | L72: =SUM(L68:L69) -> 2117112.9 | ... X72: =SUM(X68:X69) -> 2258128.6
C74: Interest Coverage Ratio | E74: n/a | F74: n/a | G74: n/a | H74: =H68/H69*-1 -> 213.65989 | I74: =I68/I69*-1 -> -232.01116 | J74: =J68/J69*-1 -> -766.34079 | K74: =K68/K69*-1 -> -703.25247 | L74: =L68/L69*-1 -> -2649.1494 | M74: =M68/M69*-1 -> -2663.4592 | N74: =N68/N69*-1 -> -2677.8405 | O74: =O68/O69*-1 -> -2692.2937 | ... X74: =X68/X69*-1 -> -2822.4885
C75: Debt Service Ratio | E75: n/a | F75: n/a | G75: n/a | H75: =+H68/(-H69-H91) -> 213.65989 | I75: =+I68/(-I69-I91) -> -232.01116 | J75: =+J68/(-J69-J91) -> -766.34079 | K75: =+K68/(-K69-K91) -> -703.25247 | L75: =+L68/(-L69-L91) -> -2649.1494 | M75: =+M68/(-M69-M91) -> -2663.4592 | N75: =+N68/(-N69-N91) -> -2677.8405 | O75: =+O68/(-O69-O91) -> -2692.2937 | ... X75: =+X68/(-X69-X91) -> -2822.4885
C76: Proceeds as a % of EBITDA | E76: n/a | F76: n/a | G76: n/a | H76: =H68/H58 -> -0.24256565 | I76: =I68/I58 -> 0.10859217 | J76: =J68/J58 -> 0.37102819 | K76: =K68/K58 -> 0.57843412 | L76: =L68/L58 -> 0.92564451 | M76: =M68/M58 -> 0.92601444 | N76: =N68/N58 -> 0.92638252 | O76: =O68/O58 -> 0.92674878 | ... X76: =X68/X58 -> 0.92996417
C78: Cash Flow Continuity
C79: Opening Cash | E79: 0 | F79: =E86 -> 337529.94 | G79: =F86 -> 174280.54 | H79: =G86 -> 7766.1518 | I79: =H86 -> 4463.0538 | J79: =I86 -> 6542.9364 | K79: =J86 -> 16584.26 | L79: =K86 -> 39943.273 | M79: =L86 -> 39943.273 | ... X79: =W86 -> 39988.273
C80: New Equity Financing | E80: =$D$38 -> 10000000 | F80: 0 | G80: 0 | H80: 0 | I80: 0 | J80: 0 | K80: 0 | L80: 0 | M80: 0 | N80: 0 | O80: 1 | P80: 2 | Q80: 3 | R80: 4 | S80: 5 | T80: 6 | U80: 7 | V80: 8 | W80: 9 | X80: 10
C81: New Debt Financing (gross) | E81: =E90 -> 0 | F81: =F90 -> 0 | G81: =G90 -> 0 | H81: =H90 -> 0 | I81: =I90 -> 0 | J81: =J90 -> 0 | K81: =K90 -> 0 | L81: =L90 -> 0 | ... X81: =X90 -> 0
C82: Capital Asset Additions | E82: =-E100 -> -9492470.1 | F82: =-F100+F96 -> 0 | G82: =-G100+G96 -> 0 | H82: =-H100+H96 -> 0 | I82: =-I100+I96 -> 0 | J82: =-J100+J96 -> 0 | K82: =-K100+K96 -> 0 | L82: =-L100+L96 -> 0 | M82: =-M100+M96 -> 0 | ... X82: =-X100+X96 -> 0
C83: Debt Repayment | E83: =E91 -> 0 | F83: =F91 -> 0 | G83: =G91 -> 0 | H83: =H91 -> 0 | I83: =I91 -> 0 | J83: =J91 -> 0 | K83: =K91 -> 0 | L83: =L91 -> 0 | ... X83: =X91 -> 0
C84: Distributions | E84: =-E120 -> 0 | F84: =-F120 -> 0 | G84: =-G120 -> 0 | H84: =-H120 -> 29727.882 | I84: =-I120 -> -18718.944 | J84: =-J120 -> -90371.916 | K84: =-K120 -> -210231.12 | L84: =-L120 -> -2117112.9 | ... X84: =-X120 -> -2258128.6
C85: =+C72 -> Funding from operations | E85: =E72 -> -170000 | F85: =F72 -> -163249.4 | G85: =G72 -> -166514.39 | H85: =H72 -> -33030.98 | I85: =I72 -> 20798.827 | J85: =J72 -> 100413.24 | K85: =K72 -> 233590.13 | L85: =L72 -> 2117112.9 | ... X85: =X72 -> 2258128.6
C86: Ending Cash | E86: =SUM(E79:E85) -> 337529.94 | F86: =SUM(F79:F85) -> 174280.54 | G86: =SUM(G79:G85) -> 7766.1518 | H86: =SUM(H79:H85) -> 4463.0538 | I86: =SUM(I79:I85) -> 6542.9364 | J86: =SUM(J79:J85) -> 16584.26 | K86: =SUM(K79:K85) -> 39943.273 | L86: =SUM(L79:L85) -> 39943.273 | ... X86: =SUM(X79:X85) -> 39998.273
C88: Debenture Continuity
C89: Opening Debt | E89: 0 | F89: =E92 -> 0 | G89: =F92 -> 0 | H89: =G92 -> 0 | I89: =H92 -> 0 | J89: =I92 -> 0 | K89: =J92 -> 0 | L89: =K92 -> 0 | M89: =L92 -> 0 | ... X89: =W92 -> 0
C90: Additions | E90: 0 | F90: 0 | G90: 0 | H90: =+E48/2 -> 0 | I90: =+E48/2 -> 0 | J90: =+E49/2 -> 0 | K90: 0 | L90: 0 | M90: =SUM(M97:M99) -> 0 | N90: =SUM(N97:N99) -> 0 | O90: =SUM(O97:O99) -> 0 | P90: =SUM(P97:P99) -> 0 | Q90: =SUM(Q97:Q99) -> 0 | R90: =SUM(R97:R99) -> 0 | S90: =SUM(S97:S99) -> 0 | T90: =SUM(T97:T99) -> 0 | ... X90: =SUM(X97:X99) -> 0
C91: Payments | E91: 0 | F91: 0 | G91: 0 | H91: 0 | L91: =-L72*$D31 -> 0 | M91: =-M72*$D31 -> 0 | N91: =-N72*$D31 -> 0 | O91: =-O72*$D31 -> 0 | P91: =-P72*$D31 -> 0 | Q91: =-Q72*$D31 -> 0 | R91: =-R72*$D31 -> 0 | S91: =-S72*$D31 -> 0 | ... X91: =-X72*$D31 -> 0
C92: Ending Debt | E92: =SUM(E89:E91) -> 0 | F92: =SUM(F89:F91) -> 0 | G92: =SUM(G89:G91) -> 0 | H92: =SUM(H89:H91) -> 0 | I92: =SUM(I89:I91) -> 0 | J92: =SUM(J89:J91) -> 0 | K92: =SUM(K89:K91) -> 0 | L92: =SUM(L89:L91) -> 0 | ... X92: =SUM(X89:X91) -> 0
C95: Asset Continuity
C96: Opening Assets | E96: =($D$43/100)*'[1]PCLP 1_250M'!E115 -> 9492470.1 | F96: =($D$43/100)*'[1]PCLP 1_250M'!F115 -> 9513938 | G96: =($D$43/100)*'[1]PCLP 1_250M'!G115 -> 9506782.3 | H96: =($D$43/100)*'[1]PCLP 1_250M'!H115 -> 12647137 | I96: =($D$43/100)*'[1]PCLP 1_250M'!I115 -> 12668327 | J96: =($D$43/100)*'[1]PCLP 1_250M'!J115 -> 20585461 | K96: =($D$43/100)*'[1]PCLP 1_250M'!K115 -> 20630268 | L96: =($D$43/100)*'[1]PCLP 1_250M'!L115 -> 36095145 | ... X96: =($D$43/100)*'[1]PCLP 1_250M'!X115 -> 45366994
C97: =+C6 -> Phase 1 - initial funding for capital assets | E97: 0 | F97: 0 | G97: 0 | H97: 0 | I97: 0 | J97: 0 | K97: 0 | L97: 0 | M97: 0 | N97: 0 | O97: 0 | P97: 0 | Q97: 0 | R97: 0 | S97: 0 | T97: 0 | U97: 0 | V97: 0 | W97: 0 | X97: 0
C98: =+C7 -> Phase 2 - first financing | E98: 0 | F98: 0 | G98: 0 | H98: =($F$7*$E$7)/$D7 -> 0 | I98: =($F$7*$E$7)/$D7 -> 0 | J98: 0 | K98: 0 | L98: 0 | M98: 0 | N98: 0 | O98: 0 | P98: 0 | Q98: 0 | R98: 0 | S98: 0 | T98: 0 | U98: 0 | V98: 0 | W98: 0 | X98: 0
C99: =+C8 -> Phase 3 - second financing | E99: 0 | F99: 0 | G99: 0 | H99: 0 | I99: 0 | J99: =($F8*$E8)/$D8 -> 0 | K99: =($F8*$E8)/$D8 -> 0 | L99: 0 | M99: 0 | N99: 0 | O99: 0 | P99: 0 | Q99: 0 | R99: 0 | S99: 0 | T99: 0 | U99: 0 | V99: 0 | W99: 0 | X99: 0
C100: Total Capital Assets | E100: =SUM(E96:E99) -> 9492470.1 | F100: =SUM(F96:F99) -> 9513938 | G100: =SUM(G96:G99) -> 9506782.3 | H100: =SUM(H96:H99) -> 12647137 | I100: =SUM(I96:I99) -> 12668327 | J100: =SUM(J96:J99) -> 20585461 | K100: =SUM(K96:K99) -> 20630268 | L100: =SUM(L96:L99) -> 36095145 | ... X100: =SUM(X96:X99) -> 45366994
C102: Total Capital Assets Generating Rent | E102: 0 | F102: 0 | G102: 0 | H102: 0 | I102: 0 | J102: 0 | K102: 0 | L102: 0 | M102: 0 | N102: 0 | O102: 0 | P102: 0 | Q102: 0 | R102: 0 | S102: 0 | T102: 0 | U102: 0 | V102: 0 | W102: 0 | X102: 0
C104: Buildings under construction | E104: 0 | F104: 0 | G104: 0 | H104: 0 | I104: 0 | J104: 0 | K104: 0 | L104: 0 | M104: 0 | N104: 0 | O104: 0 | P104: 0 | Q104: 0 | R104: 0 | S104: 0 | T104: 0 | U104: 0 | V104: 0 | W104: 0 | X104: 0
C105: FMV of building under construction | E105: =E104*(1-$D$25) -> 0 | F105: =F104*(1-$D$25) -> 0 | G105: =G104*(1-$D$25) -> 0 | H105: =H104*(1-$D$25) -> 0 | I105: =I104*(1-$D$25) -> 0 | J105: =J104*(1-$D$25) -> 0 | K105: =K104*(1-$D$25) -> 0 | L105: =L104*(1-$D$25) -> 0 | ... X105: =X104*(1-$D$25) -> 0
C106: Debt to development cost | E106: =E92/E100 -> 0 | F106: =F92/F100 -> 0 | G106: =G92/G100 -> 0 | H106: =H92/H100 -> 0 | I106: =I92/I100 -> 0 | J106: =J92/J100 -> 0 | K106: =K92/K100 -> 0 | L106: =L92/L100 -> 0 | ... X106: =X92/X100 -> 0
C108: Asset Valuation
C109: Cap Rate - Public Non Listed | E109: =E100+E86 -> 9830000 | F109: =F100+F86 -> 9688218.6 | G109: =G100+G86 -> 9514548.4 | H109: =H100+H86 -> 12651600 | I109: =I100+I86 -> 12674869 | J109: =J100+J86 -> 20602045 | K109: =K100+K86 -> 20670211 | L109: =L100+L86 -> 36135088 | ... X109: =X100+X86 -> 45406992
C110: Asset Valuation (per diluted Unit) | E110: =+E109/$D$45 -> 83.555752 | F110: =+F109/$D$45 -> 82.350599 | G110: =+G109/$D$45 -> 80.874389 | H110: =+H109/$D$45 -> 107.53956 | I110: =+I109/$D$45 -> 107.73736 | J110: =+J109/$D$45 -> 175.11896 | K110: =+K109/$D$45 -> 175.69837 | L110: =L109/$D$45 -> 307.15101 | M110: =M109/$D$45 -> 309.32112 | N110: =N109/$D$45 -> 311.50209 | O110: =O109/$D$45 -> 365.73583 | P110: =P109/$D$45 -> 367.93867 | Q110: =Q109/$D$45 -> 370.15254 | R110: =R109/$D$45 -> 372.37749 | S110: =S109/$D$45 -> 374.61356 | ... X110: =X109/$D$45 -> 385.96291
C112: Net Asset Valuations
C114: Cap Rate - Public Non Listed | E114: =E109-E92 -> 9830000 | F114: =F109-F92 -> 9688218.6 | G114: =G109-G92 -> 9514548.4 | H114: =H109-H92 -> 12651600 | I114: =I109-I92 -> 12674869 | J114: =J109-J92 -> 20602045 | K114: =K109-K92 -> 20670211 | L114: =L109-L92 -> 36135088 | ... X114: =X109-X92 -> 45406992
C115: Asset Valuation (per diluted Unit) | E115: =E114/$D45 -> 83.555752 | F115: =F114/$D45 -> 82.350599 | G115: =G114/$D45 -> 80.874389 | H115: =H114/$D45 -> 107.53956 | I115: =I114/$D45 -> 107.73736 | J115: =J114/$D45 -> 175.11896 | K115: =K114/$D45 -> 175.69837 | L115: =L114/$D45 -> 307.15101 | ... X115: =X114/$D45 -> 385.96291
C116: Distribution Yield | E116: =E122/E115 -> 0 | F116: =F122/F115 -> 0 | G116: =G122/G115 -> 0 | H116: =H122/H115 -> -0.0023497331 | I116: =I122/I115 -> 0.001476855 | J116: =J122/J115 -> 0.0043865507 | K116: =K122/K115 -> 0.010170729 | L116: =L122/L115 -> 0.05858884 | ... X116: =X122/X115 -> 0.049730857
C117: Total Expense Ratio vs NAV ( excluding financing costs ) | E117: =SUM(E63:E65)/E114 -> 0.017293998 | F117: =SUM(F63:F65)/F114 -> 0.017547086 | G117: =SUM(G63:G65)/G114 -> 0.017867375 | H117: =SUM(H63:H65)/H114 -> 0.013437036 | I117: =SUM(I63:I65)/I114 -> 0.013412367 | J117: =SUM(J63:J65)/J114 -> 0.0082516079 | K117: =SUM(K63:K65)/K114 -> 0.008224396 | L117: =SUM(L63:L65)/L114 -> 0.0047045686 | ... X117: =SUM(X63:X65)/X114 -> 0.0037439168
C119: Distribution Analysis
C120: Distribution to Limited Partners | E120: 0 | F120: 0 | G120: 0 | H120: =+H72*0.9+H91 -> -29727.882 | I120: =+I72*0.9+I91 -> 18718.944 | J120: =+J72*0.9+J91 -> 90371.916 | K120: =+K72*0.9+K91 -> 210231.12 | L120: =+L72+L91+L90 -> 2117112.9 | M120: =+M72+M91 -> 2128544.4 | N120: =+N72+N91 -> 2140033.2 | O120: =+O72+O91 -> 2151579.3 | P120: =+P72+P91 -> 2163183.3 | Q120: =+Q72+Q91 -> 2174845.2 | R120: =+R72+R91 -> 2186565.5 | S120: =+S72+S91 -> 2198344.4 | T120: =+T72+T91 -> 2210182.3 | ... X120: =+X72+X91 -> 2258128.6
C122: Distribution per Diluted Unit | E122: 0 | F122: 0 | G122: 0 | H122: =H120/$D45 -> -0.25268927 | I122: =I120/$D45 -> 0.15911245 | J122: =J120/$D45 -> 0.7681682 | K122: =K120/$D45 -> 1.7869806 | L122: =L120/$D45 -> 17.995621 | M122: =M120/$D45 -> 18.092791 | N122: =N120/$D45 -> 18.190446 | O122: =O120/$D45 -> 18.288589 | ... X122: =X120/$D45 -> 19.194266
C123: Distribution Yield (on original $100 investment) | E123: =E122/$D16 -> 0 | F123: =F122/$D16 -> 0 | G123: =G122/$D16 -> 0 | H123: =H122/$D16 -> -0.0025268927 | I123: =I122/$D16 -> 0.0015911245 | J123: =J122/$D16 -> 0.007681682 | K123: =K122/$D16 -> 0.017869806 | L123: =L122/$D16 -> 0.17995621 | ... X123: =X122/$D16 -> 0.19194266
C125: Distribution year over year growth | E125: 0 | F125: 0 | G125: 0 | H125: 0 | I125: =(I122-H122)/H122 -> -1.6296763 | J125: =(J122-I122)/I122 -> 3.827832 | K125: =(K122-J122)/J122 -> 1.3262881 | L125: =(L122-K122)/K122 -> 9.0704069 | M125: =(M122-L122)/L122 -> 0.0053996035 | N125: =(N122-M122)/M122 -> 0.0053974574 | O125: =(O122-N122)/N122 -> 0.0053953236 | P125: =(P122-O122)/O122 -> 0.0053932115 | ... S125: =(S122-R122)/R122 -> 0.0053869471 | T125: =+(T122-S122)/S122 -> 0.0053848827 | U125: =+(U122-T122)/T122 -> 0.0053828301 | V125: =+(V122-U122)/U122 -> 0.0053807891 | W125: =+(W122-V122)/V122 -> 0.0053787598 | X125: =+(X122-W122)/W122 -> 0.005376742
C127: Earnings Before Taxes, Depreciation and Interest on the Debt | E127: =E68/$D$45 -> -1.445013 | F127: =F68/$D$45 -> -1.445013 | G127: =G68/$D$45 -> -1.445013 | H127: =H68/$D$45 -> -0.28208611 | I127: =I68/$D$45 -> 0.17603289 | J127: =J68/$D$45 -> 0.85240792 | K127: =K68/$D$45 -> 1.9827146 | L127: =L68/$D$45 -> 17.988831 | ... X127: =X68/$D$45 -> 19.187468
...

Sheet SPV_Compensations_2&20
C1: Cash Flow and Valuation
C2: Woodfine Professional Centres Limited Partnership
C3: January 6, 2026
D5: Build Time | E5: Gross Cost per sq. ft. | F5: Portfolio additions in sf. | G5: Capital investment
C6: Phase 1 - initial funding for capital assets | D6: 1 | E6: 310 | F6: =$D$43/$E6 -> 31612.903 | G6: =+F6*E6 -> 9800000 | O6: SPV Arrangements - Asset Manager Dilution
C7: Phase 2 - first financing | D7: 2 | E7: =+E6 -> 310 | F7: =$D$48/$E7 -> 0 | G7: =+F7*E7 -> 0 | O7: Unit-based Compensation | Q7: =D21 -> 0 | X7: Management Fee (2% NAV) | Z7: =M63 -> 2693097.5
C8: Phase 3 - second financing | D8: 2 | E8: =+E7 -> 310 | F8: =$D$49/$E8 -> 0 | G8: =+F8*E8 -> 0 | O8: =C23 -> Board of Directors Expense | Q8: =D23 -> 30000 | X8: Management Carry (20%) | Z8: =N100 -> 7454845.4
F9: =SUM(F6:F8) -> 31612.903 | G9: =SUM(G6:G8) -> 9800000 | O9: =C24 -> Admin Costs | Q9: =D24 -> 20000
C10: Development Yield | D10: 0.105 | O10: Working Capital Reserve | Q10: =D34 -> 0.02
C12: Cap Rate - Public Non Listed | D12: 0.0625 | S12: Y1 | T12: Y2 | U12: Y3 | V12: Y4 | W12: Y5 | X12: Y6 | Y12: Y7 | Z12: Y8 | AA12: Y9 | AB12: Y10
O13: Revenue | S13: - | T13: - | U13: - | V13: =H57/$D45 -> 1.4128426 | W13: =I57/$D45 -> 1.9694125 | X13: =J57/$D45 -> 2.7911421 | Y13: =K57/$D45 -> 4.1643543 | Z13: =L57/$D45 -> 23.610223 | AA13: 0 | AB13: 0
O14: Distributions | S14: - | T14: - | U14: - | V14: =H122 -> -1.540413 | W14: =I122 -> -1.046106 | X14: =J122 -> -1.7823518 | Y14: =K122 -> -0.56141923 | Z14: =L122 -> 15.943835 | AA14: 0 | AB14: 0
C15: Total Equity Financing - 1 year | D15: 10000000
C16: Cost per Unit | D16: 100 | O16: Distribution Yield on Initial Capital | S16: - | T16: - | U16: - | V16: =V14/100 -> -0.01540413 | W16: =W14/100 -> -0.01046106 | X16: =X14/100 -> -0.017823518 | Y16: =Y14/100 -> -0.0056141923 | Z16: =Z14/100 -> 0.15943835 | AA16: =AA14/100 -> 0 | AB16: =AB14/100 -> 0
C17: Issuing Agents Fee | D17: 0
O18: Asset Value | S18: =E110 -> 98.026488 | T18: =F110 -> 98.248182 | U18: =G110 -> 98.174287 | V18: =H110 -> 130.60398 | W18: =I110 -> 130.8228 | X18: =J110 -> 212.58118 | Y18: =K110 -> 213.04388 | Z18: =L110 -> 290.58007 | AA18: 0 | AB18: 0
C19: Advisory Fee as percentage of Gross Funded Value | D19: 0.02 | O19: Total Debt | S19: =E92/$D45 -> 0 | T19: =F92/$D45 -> 0 | U19: =G92/$D45 -> 0 | V19: =H92/$D45 -> 0 | W19: =I92/$D45 -> 0 | X19: =J92/$D45 -> 0 | Y19: =K92/$D45 -> 0 | Z19: =L92/$D45 -> 0 | AA19: 0 | AB19: 0
C21: Benetti Holdings Dilution | D21: 0 | O21: Net Asset Value (NAV) | S21: =E115 -> 98.026488 | T21: =F115 -> 98.248182 | U21: =G115 -> 98.174287 | V21: =H115 -> 130.60398 | W21: =I115 -> 130.8228 | X21: =J115 -> 212.58118 | Y21: =K115 -> 213.04388 | Z21: =L115 -> 290.58007 | AA21: 0 | AB21: 0
C23: Board of Directors Expense | D23: 30000 | O23: Market Value | Q23: 0.0695 | S23: 100 | T23: 100 | U23: 100 | V23: 125.8 | W23: 132.1 | X23: 171.5 | Y23: 177.3 | Z23: =Z14/Q23 -> 229.4077 | AA23: =AA14/Q23 -> 0 | AB23: =AB14/Q23 -> 0
C24: Admin Costs | D24: 20000 | V24: =(V23-V21)/V21 -> -0.036782806 | W24: =(W23-W21)/W21 -> 0.0097627899 | X24: =(X23-X21)/X21 -> -0.19324936 | Y24: =(Y23-Y21)/Y21 -> -0.16777709 | Z24: =(Z23-Z21)/Z21 -> -0.21051812 | AA24: 0 | AB24: 0
C25: Discount to FMV for buildings under cost | D25: 0 | O25: Discount / Premium vs. Net Asset Value (NAV)
C27: Issue Costs as a Percentage of Gross Funded Value | D27: 0 | O27: Compounded Annual Return (Excluding Distributions) | Z27: =((Z23/100)^(1/8))-1 -> 0.10936893
C28: Issuing Agents Fee - First Secured Mortgage Debentures | D28: 0 | O28: Distribution Yield to Buyers at Market Value | Z28: =Z14/Z23 -> 0.0695 | AA28: 0 | AB28: 0
C29: Interest Paid to the First Secured Mortgage Debentures | D29: 0
C30: Interest earned on Cash on Hand | D30: 0 | O30: Interest Coverage Ratio | S30: - | T30: - | U30: - | V30: 0 | W30: 0 | X30: 0 | Y30: 0 | Z30: 0 | AA30: 0 | AB30: 0
C31: Debenture Buy Back (% of EBITDA) | D31: 0 | O31: Debt vs. Development Cost | S31: - | T31: - | U31: - | V31: =H106 -> 0 | W31: =I106 -> 0 | X31: =J106 -> 0 | Y31: =K106 -> 0 | Z31: =L106 -> 0 | AA31: 0 | AB31: 0
O32: Debt to Asset Value | S32: - | T32: - | U32: - | V32: =V19/V18 -> 0 | W32: =W19/W18 -> 0 | X32: =X19/X18 -> 0 | Y32: =Y19/Y18 -> 0 | Z32: =Z19/Z18 -> 0 | AA32: 0 | AB32: 0
C33: Minimum cash balance | D33: 15000
C34: Working Capital Reserve during development | D34: 0.02 | O34: Total Expense Ratio (NAV) | S34: =E117 -> 0.025401552 | T34: =F117 -> 0.025293582 | U34: =G117 -> 0.025199797 | V34: =H117 -> 0.023922798 | W34: =I117 -> 0.023938888 | X34: =J117 -> 0.022445698 | Y34: =K117 -> 0.022474963 | Z34: =L117 -> 0.026383045 | AA34: 0 | AB34: 0
O35: Total Square Foot - $10 Million Gross Funded Value | S35: - | T35: - | U35: - | V35: =+F6 -> 31612.903 | W35: =V35 -> 31612.903 | X35: =+W35+F7 -> 31612.903 | Y35: =X35 -> 31612.903 | Z35: =(D43+D48+D49)/E6 -> 31612.903 | AA35: =Z35 -> 31612.903 | AB35: =AA35 -> 31612.903
C37: Equity Proceeds
C38: Partner Contributions | D38: =D15-D32 -> 10000000 | O38: Year 8 | S38: $ | T38: %
C39: Issuing Agents Fees | D39: =D17*D38 -> 0
C40: Issue Costs | D40: =+D27*D38 -> 0 | O40: Revenue | S40: =Z13 -> 23.610223 | T40: =S40/S40 -> 1
C41: Net Proceeds | D41: =D38-D39-D40 -> 10000000
C42: Working Capital | D42: =D34*D38 -> 200000 | P42: Advisory Fee | S42: =L63/D45 -> 7.1663823 | T42: =S42/S40 -> 0.30352879
C43: Net Equity Funding | D43: =D41-D42 -> 9800000
P44: Operating and Administrative Expense | S44: =(L64+L65)/D45 -> 0.500005 | T44: =S44/S40 -> 0.021177479
C45: Number of Diluted Units | D45: =ROUND(+((D38/D16)/(1-D21)),0)-1 -> 99999 | P45: Interest Payments | S45: =(L69/D45)*-1 -> 0 | T45: =S45/S40 -> 0
C47: Debt Proceeds | E47: Gross borrowing | O47: Distributable Income
C48: Initial Financing (net of 3% cost) | D48: =+E48-E48*0.03 -> 0 | E48: 0
C49: Secondary Financing (net of 3% cost) | D49: =+E49-E49*0.03 -> 0 | E49: 0 | P49: Repurchase Of Debentures | S49: =(#REF!/D45)*-1 -> #REF! | T49: =S49/S40 -> #REF!
C50: Total (max) Debt Financing | E50: =SUM(E48:E49) -> 0 | P50: Distributions | S50: =(L84/D45)*-1 -> -14.349453 | T50: =S50/S40 -> -0.60776443
E55: 1 | F55: 2 | G55: 3 | H55: 4 | I55: 5 | J55: 6 | K55: 7 | L55: 8
C56: Income
C57: Net proceeds from operations | E57: =($D$43/100)*('[1]PCLP 1_250M'!E123*100) -> 0 | F57: =($D$43/100)*('[1]PCLP 1_250M'!F123*100) -> 0 | G57: =($D$43/100)*('[1]PCLP 1_250M'!G123*100) -> 0 | H57: =($D$43/100)*('[1]PCLP 1_250M'!H123*100) -> 141282.85 | I57: =($D$43/100)*('[1]PCLP 1_250M'!I123*100) -> 196939.28 | J57: =($D$43/100)*('[1]PCLP 1_250M'!J123*100) -> 279111.42 | K57: =($D$43/100)*('[1]PCLP 1_250M'!K123*100) -> 416431.27 | L57: =($D$43/100)*('[1]PCLP 1_250M'!L123*100) -> 2360998.7 | M57: 37274227
C58: Income Continuity | D58: (Note-1) | E58: 0 | F58: 0 | G58: 0 | H58: =SUM(H57:H57) -> 141282.85 | I58: =SUM(I57:I57) -> 196939.28 | J58: =SUM(J57:J57) -> 279111.42 | K58: =SUM(K57:K57) -> 416431.27 | L58: =SUM(L57:L57) -> 2360998.7
C60: Expenses & Fees | F60: =SUM(E61:H65) -> 1057335.2
C61: Issue Costs | E61: =$D27*$D15 -> 0 | F61: 0 | G61: 0 | H61: 0 | I61: 0 | J61: 0 | K61: 0 | L61: 0
C62: Financing costs | E62: =D39 -> 0 | F62: 0 | G62: 0 | H62: =D28*E48 -> 0 | I62: 0 | J62: =D28*E49 -> 0 | K62: 0 | L62: 0
C63: Advisory Fees | E63: =E108*$D19 -> 199000 | F63: =F108*$D19 -> 198502.36 | G63: =G108*$D19 -> 197394.74 | H63: =H108*$D19 -> 262438.14 | I63: =I108*$D19 -> 263172.12 | J63: =J108*$D19 -> 427148.52 | K63: =K108*$D19 -> 428810.56 | L63: =L108*$D19 -> 716631.06 | M63: =SUM(E63:L63) -> 2693097.5
C64: Admin and Compliance | E64: =$D24 -> 20000 | F64: =$D24 -> 20000 | G64: =$D24 -> 20000 | H64: =$D24 -> 20000 | I64: =$D24 -> 20000 | J64: =$D24 -> 20000 | K64: =$D24 -> 20000 | L64: =$D24 -> 20000
C65: Board of Directors | E65: =+$D23 -> 30000 | F65: =+$D23 -> 30000 | G65: =+$D23 -> 30000 | H65: =+$D23 -> 30000 | I65: =+$D23 -> 30000 | J65: =+$D23 -> 30000 | K65: =+$D23 -> 30000 | L65: =+$D23 -> 30000
C66: Total Expenses | E66: =SUM(E61:E65) -> 249000 | F66: =SUM(F61:F65) -> 248502.36 | G66: =SUM(G61:G65) -> 247394.74 | H66: =SUM(H61:H65) -> 312438.14 | I66: =SUM(I61:I65) -> 313172.12 | J66: =SUM(J61:J65) -> 477148.52 | K66: =SUM(K61:K65) -> 478810.56 | L66: =SUM(L61:L65) -> 766631.06
C68: Earnings before interest, taxes and depreciation (EBITDA) | E68: =+E57-E66 -> -249000 | F68: =+F57-F66 -> -248502.36 | G68: =+G57-G66 -> -247394.74 | H68: =+H58-H66 -> -171155.29 | I68: =+I58-I66 -> -116232.84 | J68: =+J58-J66 -> -198037.1 | K68: =+K58-K66 -> -62379.291 | L68: =+L58-L66 -> 1594367.6
C69: Cost of Debenture Debt net of interest on funds on deposit | E69: =(SUM(E79)*$D$30)-((E89+E92)/2*$D$29) -> 0 | F69: =(SUM(F79)*$D$30)-((F89+F92)/2*$D$29) -> 0 | G69: =(SUM(G79)*$D$30)-((G89+G92)/2*$D$29) -> 0 | H69: =(SUM(H79)*$D$30)-((H89+H92)/2*$D$29) -> 0 | I69: =(SUM(I79)*$D$30)-((I89+I92)/2*$D$29) -> 0 | J69: =(SUM(J79)*$D$30)-((J89+J92)/2*$D$29) -> 0 | K69: =(SUM(K79)*$D$30)-((K89+K92)/2*$D$29) -> 0 | L69: =(SUM(L79)*$D$30)-(L89*$D$29) -> 0
C70: Percentage Interest Payable - net of interest income | H70: =(H69/H92)*-1 -> #DIV/0! | I70: =(I69/I92)*-1 -> #DIV/0! | J70: =(J69/J92)*-1 -> #DIV/0! | K70: =(K69/K92)*-1 -> #DIV/0! | L70: =(L69/L92)*-1 -> #DIV/0!
C72: Funding from operations | E72: =SUM(E68:E69) -> -249000 | F72: =SUM(F68:F69) -> -248502.36 | G72: =SUM(G68:G69) -> -247394.74 | H72: =SUM(H68:H69) -> -171155.29 | I72: =SUM(I68:I69) -> -116232.84 | J72: =SUM(J68:J69) -> -198037.1 | K72: =SUM(K68:K69) -> -62379.291 | L72: =SUM(L68:L69) -> 1594367.6 | M72: =-L72*10% -> -159436.76 | N72: =L72+M72 -> 1434930.8
C74: Interest Coverage Ratio | E74: n/a | F74: n/a | G74: n/a | H74: =H68/H69*-1 -> #DIV/0! | I74: =I68/I69*-1 -> #DIV/0! | J74: =J68/J69*-1 -> #DIV/0! | K74: =K68/K69*-1 -> #DIV/0! | L74: =L68/L69*-1 -> #DIV/0!
C75: Debt Service Ratio | E75: n/a | F75: n/a | G75: n/a | H75: =+H68/(-H69-H91) -> #DIV/0! | I75: =+I68/(-I69-I91) -> #DIV/0! | J75: =+J68/(-J69-J91) -> #DIV/0! | K75: =+K68/(-K69-K91) -> #DIV/0! | L75: =+L68/(-L69-L91) -> #DIV/0!
C76: Proceeds as a % of EBITDA | E76: n/a | F76: n/a | G76: n/a | H76: =H68/H58 -> -1.2114372 | I76: =I68/I58 -> -0.59019635 | J76: =J68/J58 -> -0.70952706 | K76: =K68/K58 -> -0.14979493 | L76: =L68/L58 -> 0.67529373
C78: Cash Flow Continuity
C79: Opening Cash | E79: 0 | F79: =E86 -> -51550.745 | G79: =F86 -> -300053.1 | H79: =G86 -> -547447.84 | I79: =H86 -> -564563.37 | J79: =I86 -> -576186.66 | K79: =J86 -> -595990.37 | L79: =K86 -> -602228.3
C80: New Equity Financing | E80: =$D$38 -> 10000000 | F80: 0 | G80: 0 | H80: 0 | I80: 0 | J80: 0 | K80: 0 | L80: 0
C81: New Debt Financing (gross) | E81: =E90 -> 0 | F81: =F90 -> 0 | G81: =G90 -> 0 | H81: =H90 -> 0 | I81: =I90 -> 0 | J81: =J90 -> 0 | K81: =K90 -> 0 | L81: =L90 -> 0
C82: Capital Asset Additions | E82: =-E100 -> -9802550.7 | F82: =-F100+F96 -> 0 | G82: =-G100+G96 -> 0 | H82: =-H100+H96 -> 0 | I82: =-I100+I96 -> 0 | J82: =-J100+J96 -> 0 | K82: =-K100+K96 -> 0 | L82: 0
C83: Debt Repayment | E83: =E91 -> 0 | F83: =F91 -> 0 | G83: =G91 -> 0 | H83: =H91 -> 0 | I83: =I91 -> 0 | J83: =J91 -> 0 | K83: =K91 -> 0 | L83: -7454845.4 | M83: =L83-M63 -> -10147943
C84: Distributions | E84: =-E120 -> 0 | F84: =-F120 -> 0 | G84: =-G120 -> 0 | H84: =-H120 -> 154039.76 | I84: =-I120 -> 104609.56 | J84: =-J120 -> 178233.39 | K84: =-K120 -> 56141.362 | L84: 1434931
C85: =+C72 -> Funding from operations | E85: =E72 -> -249000 | F85: =F72 -> -248502.36 | G85: =G72 -> -247394.74 | H85: =H72 -> -171155.29 | I85: =I72 -> -116232.84 | J85: =J72 -> -198037.1 | K85: =K72 -> -62379.291 | L85: =-L72 -> -1594367.6
C86: Ending Cash | E86: =SUM(E79:E85) -> -51550.745 | F86: =SUM(F79:F85) -> -300053.1 | G86: =SUM(G79:G85) -> -547447.84 | H86: =SUM(H79:H85) -> -564563.37 | I86: =SUM(I79:I85) -> -576186.66 | J86: =SUM(J79:J85) -> -595990.37 | K86: =SUM(K79:K85) -> -602228.3 | L86: =SUM(L79:L85) -> -8216510.3 | M86: =L82-L86 -> 8216510.3
C88: Debenture Continuity
C89: Opening Debt | E89: 0 | F89: =E92 -> 0 | G89: =F92 -> 0 | H89: =G92 -> 0 | I89: =H92 -> 0 | J89: =I92 -> 0 | K89: =J92 -> 0 | L89: =K92 -> 0
C90: Additions | E90: 0 | F90: 0 | G90: 0 | H90: =+E48/2 -> 0 | I90: =+E48/2 -> 0 | J90: =+E49/2 -> 0 | K90: 0 | L90: 0
C91: Payments | E91: 0 | F91: 0 | G91: 0 | H91: 0 | L91: =-L72*$D31 -> 0
C92: Ending Debt | E92: =SUM(E89:E91) -> 0 | F92: =SUM(F89:F91) -> 0 | G92: =SUM(G89:G91) -> 0 | H92: =SUM(H89:H91) -> 0 | I92: =SUM(I89:I91) -> 0 | J92: =SUM(J89:J91) -> 0 | K92: =SUM(K89:K91) -> 0 | L92: =SUM(L89:L91) -> 0
C95: Asset Continuity
C96: Opening Assets | E96: =($D$43/100)*'[1]PCLP 1_250M'!E115 -> 9802550.7 | F96: =($D$43/100)*'[1]PCLP 1_250M'!F115 -> 9824720 | G96: =($D$43/100)*'[1]PCLP 1_250M'!G115 -> 9817330.5 | H96: =($D$43/100)*'[1]PCLP 1_250M'!H115 -> 13060267 | I96: =($D$43/100)*'[1]PCLP 1_250M'!I115 -> 13082150 | J96: =($D$43/100)*'[1]PCLP 1_250M'!J115 -> 21257905 | K96: =($D$43/100)*'[1]PCLP 1_250M'!K115 -> 21304175 | L96: =($D$43/100)*'[1]PCLP 1_250M'!L115 -> 37274227
C97: =+C6 -> Phase 1 - initial funding for capital assets | E97: 0 | F97: 0 | G97: 0 | H97: 0 | I97: 0 | J97: 0 | K97: 0 | L97: 0
C98: =+C7 -> Phase 2 - first financing | E98: 0 | F98: 0 | G98: 0 | H98: =($F$7*$E$7)/$D7 -> 0 | I98: =($F$7*$E$7)/$D7 -> 0 | J98: 0 | K98: 0 | L98: 0
C99: =+C8 -> Phase 3 - second financing | E99: 0 | F99: 0 | G99: 0 | H99: 0 | I99: 0 | J99: =($F8*$E8)/$D8 -> 0 | K99: =($F8*$E8)/$D8 -> 0 | L99: -8216510.3
C100: Total Capital Assets | E100: =SUM(E96:E99) -> 9802550.7 | F100: =SUM(F96:F99) -> 9824720 | G100: =SUM(G96:G99) -> 9817330.5 | H100: =SUM(H96:H99) -> 13060267 | I100: =SUM(I96:I99) -> 13082150 | J100: =SUM(J96:J99) -> 21257905 | K100: =SUM(K96:K99) -> 21304175 | L100: =SUM(L96:L99) -> 29057717 | M100: 37274227 | N100: =M100*20% -> 7454845.4
C102: Total Capital Assets Generating Rent | E102: 0 | F102: 0 | G102: 0 | H102: 0 | I102: 0 | J102: 0 | K102: 0 | L102: 0 | N102: =N100+M63 -> 10147943
C104: Buildings under construction | E104: 0 | F104: 0 | G104: 0 | H104: 0 | I104: 0 | J104: 0 | K104: 0 | L104: 0
C105: FMV of building under construction | E105: =E104*(1-$D$25) -> 0 | F105: =F104*(1-$D$25) -> 0 | G105: =G104*(1-$D$25) -> 0 | H105: =H104*(1-$D$25) -> 0 | I105: =I104*(1-$D$25) -> 0 | J105: =J104*(1-$D$25) -> 0 | K105: =K104*(1-$D$25) -> 0 | L105: =L104*(1-$D$25) -> 0
C106: Debt to development cost | E106: =E92/E100 -> 0 | F106: =F92/F100 -> 0 | G106: =G92/G100 -> 0 | H106: =H92/H100 -> 0 | I106: =I92/I100 -> 0 | J106: =J92/J100 -> 0 | K106: =K92/K100 -> 0 | L106: =L92/L100 -> 0
M107: 35831553 | N107: =M107*20% -> 7166310.6
C108: Asset Valuation | E108: 9950000 | F108: 9925118 | G108: 9869737 | H108: 13121907 | I108: 13158606 | J108: 21357426 | K108: 21440528 | L108: 35831553
C109: Cap Rate - Public Non Listed | E109: =E100 -> 9802550.7 | F109: =F100 -> 9824720 | G109: =G100 -> 9817330.5 | H109: =H100 -> 13060267 | I109: =I100 -> 13082150 | J109: =J100 -> 21257905 | K109: =K100 -> 21304175 | L109: =L100 -> 29057717
C110: Asset Valuation (per diluted Unit) | E110: =+E109/$D$45 -> 98.026488 | F110: =+F109/$D$45 -> 98.248182 | G110: =+G109/$D$45 -> 98.174287 | H110: =+H109/$D$45 -> 130.60398 | I110: =+I109/$D$45 -> 130.8228 | J110: =+J109/$D$45 -> 212.58118 | K110: =+K109/$D$45 -> 213.04388 | L110: =L109/$D$45 -> 290.58007
C112: Net Asset Valuations
C114: Cap Rate - Public Non Listed | E114: =E109-E92 -> 9802550.7 | F114: =F109-F92 -> 9824720 | G114: =G109-G92 -> 9817330.5 | H114: =H109-H92 -> 13060267 | I114: =I109-I92 -> 13082150 | J114: =J109-J92 -> 21257905 | K114: =K109-K92 -> 21304175 | L114: =L109-L92 -> 29057717
C115: Asset Valuation (per diluted Unit) | E115: =E114/$D45 -> 98.026488 | F115: =F114/$D45 -> 98.248182 | G115: =G114/$D45 -> 98.174287 | H115: =H114/$D45 -> 130.60398 | I115: =I114/$D45 -> 130.8228 | J115: =J114/$D45 -> 212.58118 | K115: =K114/$D45 -> 213.04388 | L115: =L114/$D45 -> 290.58007
C116: Distribution Yield | E116: =E122/E115 -> 0 | F116: =F122/F115 -> 0 | G116: =G122/G115 -> 0 | H116: =H122/H115 -> -0.011794533 | I116: =I122/I115 -> -0.0079963585 | J116: =J122/J115 -> -0.0083843348 | K116: =K122/K115 -> -0.0026352281 | L116: =L122/L115 -> 0.054868991
C117: Total Expense Ratio vs NAV ( excluding financing costs ) | E117: =SUM(E63:E65)/E114 -> 0.025401552 | F117: =SUM(F63:F65)/F114 -> 0.025293582 | G117: =SUM(G63:G65)/G114 -> 0.025199797 | H117: =SUM(H63:H65)/H114 -> 0.023922798 | I117: =SUM(I63:I65)/I114 -> 0.023938888 | J117: =SUM(J63:J65)/J114 -> 0.022445698 | K117: =SUM(K63:K65)/K114 -> 0.022474963 | L117: =SUM(L63:L65)/L114 -> 0.026383045
C119: Distribution Analysis
C120: Distribution to Limited Partners | E120: 0 | F120: 0 | G120: 0 | H120: =+H72*0.9+H91 -> -154039.76 | I120: =+I72*0.9+I91 -> -104609.56 | J120: =+J72*0.9+J91 -> -178233.39 | K120: =+K72*0.9+K91 -> -56141.362 | L120: =+L72+L91+L90 -> 1594367.6
C122: Distribution per Diluted Unit | E122: 0 | F122: 0 | G122: 0 | H122: =H120/$D45 -> -1.540413 | I122: =I120/$D45 -> -1.046106 | J122: =J120/$D45 -> -1.7823518 | K122: =K120/$D45 -> -0.56141923 | L122: =L120/$D45 -> 15.943835
C123: Distribution Yield (on original $100 investment) | E123: =E122/$D16 -> 0 | F123: =F122/$D16 -> 0 | G123: =G122/$D16 -> 0 | H123: =H122/$D16 -> -0.01540413 | I123: =I122/$D16 -> -0.01046106 | J123: =J122/$D16 -> -0.017823518 | K123: =K122/$D16 -> -0.0056141923 | L123: =L122/$D16 -> 0.15943835
C125: Distribution year over year growth | E125: 0 | F125: 0 | G125: 0 | H125: 0 | I125: =(I122-H122)/H122 -> -0.3208925 | J125: =(J122-I122)/I122 -> 0.70379644 | K125: =(K122-J122)/J122 -> -0.6850121 | L125: =(L122-K122)/K122 -> -29.399161
C127: Earnings Before Taxes, Depreciation and Interest on the Debt | E127: =E68/$D$45 -> -2.4900249 | F127: =F68/$D$45 -> -2.4850485 | G127: =G68/$D$45 -> -2.4739721 | H127: =H68/$D$45 -> -1.71157 | I127: =I68/$D$45 -> -1.1623401 | J127: =J68/$D$45 -> -1.9803908 | K127: =K68/$D$45 -> -0.62379915 | L127: =L68/$D$45 -> 15.943835
...
